<?xml version="1.0" encoding="utf-8"?><Sport Name="Snooker" PageTitle="Filtered applied. MarketID: 82 In-Running." TimeStamp="25/06/20 13:19:40"><EventGroup name="World Championship 2020" ID="20645861"><Event Name="World Championship 2020" ID="-1248191900"><Market Name="To Win Outright" ID="82" FID="80486371" StartTime="10/08/20 12:00:00" EventComment="" PlaceTerms="2, 1/2"><Participant Name="Judd Trump" Odds="5/2" OddsDecimal="3.50" OddsAmerican="250" Handicap="" ID="69358207" LastUpdated="05/04/20 10:43:59" AVG="9AFF7629F61018BCEBB613F9FE8903D0CF39FD49" /><Participant Name="Ronnie O'Sullivan" Odds="9/2" OddsDecimal="5.50" OddsAmerican="450" Handicap="" ID="69358633" LastUpdated="05/04/20 10:44:05" AVG="D21A95FE3FF9D76BA05BFEA1178469C078972F9D" /><Participant Name="Neil Robertson" Odds="9/2" OddsDecimal="5.50" OddsAmerican="450" Handicap="" ID="69358572" LastUpdated="05/04/20 10:44:04" AVG="99B31D91C3464E5C1CE41DCE9E7765B457F1AC5A" /><Participant Name="Mark Selby" Odds="8/1" OddsDecimal="9.00" OddsAmerican="800" Handicap="" ID="69358473" LastUpdated="05/04/20 10:44:01" AVG="FB23C0AE3654B31CCC0032C13CA02C27E4EA05B7" /><Participant Name="John Higgins" Odds="14/1" OddsDecimal="15.00" OddsAmerican="1400" Handicap="" ID="69358167" LastUpdated="05/04/20 10:43:59" AVG="B81A9B86EAADFE594187293D5DBD4C05ECC5C73D" /><Participant Name="Shaun Murphy" Odds="14/1" OddsDecimal="15.00" OddsAmerican="1400" Handicap="" ID="69358698" LastUpdated="20/06/20 21:39:20" AVG="38C9B6DDD752DC61F2CA86E94E6E2EF242CBB21F" /><Participant Name="Ding Junhui" Odds="16/1" OddsDecimal="17.00" OddsAmerican="1600" Handicap="" ID="69357941" LastUpdated="20/06/20 21:39:20" AVG="9C25EF0062D6F9CDFFA4239B7A6321214C2172B2" /><Participant Name="Mark Allen" Odds="18/1" OddsDecimal="19.00" OddsAmerican="1800" Handicap="" ID="69358428" LastUpdated="05/04/20 10:44:01" AVG="3049E34CBBE65AA67C878213EE07C4576DEB2A20" /><Participant Name="Kyren Wilson" Odds="20/1" OddsDecimal="21.00" OddsAmerican="2000" Handicap="" ID="69358289" LastUpdated="05/04/20 10:44:00" AVG="CC116DE22B34D5CD04AF483B551DD766B4597E19" /><Participant Name="Mark Williams" Odds="28/1" OddsDecimal="29.00" OddsAmerican="2800" Handicap="" ID="69358474" LastUpdated="05/04/20 10:44:01" AVG="8E78C25E602A3FDB03E78A7A8529C15074EE49F0" /><Participant Name="David Gilbert" Odds="28/1" OddsDecimal="29.00" OddsAmerican="2800" Handicap="" ID="69357940" LastUpdated="05/04/20 10:43:56" AVG="579D935B41EE922668A76BE6D4B59EDC09764DC7" /><Participant Name="Stuart Bingham" Odds="28/1" OddsDecimal="29.00" OddsAmerican="2800" Handicap="" ID="69358704" LastUpdated="05/04/20 10:44:07" AVG="3745A82D4602D2C47100ED12D29016EF42459138" /><Participant Name="Barry Hawkins" Odds="33/1" OddsDecimal="34.00" OddsAmerican="3300" Handicap="" ID="69357817" LastUpdated="05/04/20 10:43:55" AVG="A065ACF80E344B01CE389D03DCCF1FCD5A7069A3" /><Participant Name="Yan Bingtao" Odds="40/1" OddsDecimal="41.00" OddsAmerican="4000" Handicap="" ID="69358717" LastUpdated="05/04/20 10:44:07" AVG="DC9D44C2D75DA335FAF4AAEB3BA3C381D2D4441A" /><Participant Name="Stephen Maguire" Odds="40/1" OddsDecimal="41.00" OddsAmerican="4000" Handicap="" ID="69358703" LastUpdated="24/06/20 22:51:17" AVG="AA28C22191E2AC8B1D42AE1B6DDD3131F815E213" /><Participant Name="Jack Lisowski" Odds="50/1" OddsDecimal="51.00" OddsAmerican="5000" Handicap="" ID="69357998" LastUpdated="22/06/20 11:53:35" AVG="DAA8D825D2020F9291C068B2CB51614B4262091A" /><Participant Name="Graeme Dott" Odds="66/1" OddsDecimal="67.00" OddsAmerican="6600" Handicap="" ID="69357990" LastUpdated="22/06/20 11:52:59" AVG="2888C6647B3C27ECD52DBA1687D3131C16C6F600" /><Participant Name="Ali Carter" Odds="66/1" OddsDecimal="67.00" OddsAmerican="6600" Handicap="" ID="69357723" LastUpdated="22/06/20 11:52:59" AVG="77391AC87027B2FFAEB7E5752413A6397E6B5357" /><Participant Name="Joe Perry" Odds="100/1" OddsDecimal="101.00" OddsAmerican="10000" Handicap="" ID="69358122" LastUpdated="05/04/20 10:43:59" AVG="0405A2849EAA21311C435520716D81BF0CFCCC20" /><Participant Name="Gary Wilson" Odds="100/1" OddsDecimal="101.00" OddsAmerican="10000" Handicap="" ID="69357988" LastUpdated="05/04/20 10:43:57" AVG="87767E0855AEF2F2E50250D2EB2BC786C474677C" /><Participant Name="Ryan Day" Odds="100/1" OddsDecimal="101.00" OddsAmerican="10000" Handicap="" ID="69358662" LastUpdated="11/06/20 11:27:19" AVG="F599799EAF917DC3257DF90393191F955D4CED19" /><Participant Name="Luca Brecel" Odds="100/1" OddsDecimal="101.00" OddsAmerican="10000" Handicap="" ID="69358364" LastUpdated="11/06/20 22:19:59" AVG="729DE55337F6B20D90FA932ECD6ED787A716BBE0" /><Participant Name="Thepchaiya Un-Nooh" Odds="125/1" OddsDecimal="126.00" OddsAmerican="12500" Handicap="" ID="69358708" LastUpdated="11/06/20 22:19:59" AVG="BDA2FEA2670BE3A0E8AB3369A7962EEBDDD3E6A4" /><Participant Name="Zhou Yuelong" Odds="150/1" OddsDecimal="151.00" OddsAmerican="15000" Handicap="" ID="69358788" LastUpdated="20/06/20 21:39:20" AVG="C7DE1E4191C4647B44930658589542320005D7CD" /><Participant Name="Zhao Xintong" Odds="150/1" OddsDecimal="151.00" OddsAmerican="15000" Handicap="" ID="69358761" LastUpdated="20/06/20 21:39:20" AVG="4048A635D4DBA9AA32DB5CE4B8711121C2F37F80" /><Participant Name="Yuan Sijun" Odds="200/1" OddsDecimal="201.00" OddsAmerican="20000" Handicap="" ID="69358737" LastUpdated="20/06/20 21:39:20" AVG="BDCD673944D3AF7D29FE42EECE502A9D145BAF35" /><Participant Name="Sam Craigie" Odds="200/1" OddsDecimal="201.00" OddsAmerican="20000" Handicap="" ID="69358691" LastUpdated="20/06/20 21:39:20" AVG="D48F3F39BD48703DC0D8D7F98EC618D3F05B89E0" /><Participant Name="Martin Gould" Odds="200/1" OddsDecimal="201.00" OddsAmerican="20000" Handicap="" ID="69358475" LastUpdated="20/06/20 21:39:20" AVG="5CF370F2677A8714328BD7B011D1AB76EF92DBE0" /><Participant Name="Liang Wenbo" Odds="200/1" OddsDecimal="201.00" OddsAmerican="20000" Handicap="" ID="69358341" LastUpdated="20/06/20 21:39:20" AVG="3F4A7A43A7352E09B59698E994CEF861D0C70DA5" /><Participant Name="Ricky Walden" Odds="200/1" OddsDecimal="201.00" OddsAmerican="20000" Handicap="" ID="69358602" LastUpdated="20/06/20 21:39:20" AVG="A0060010A41DB4764F9D4970FE4637035B30DFB9" /><Participant Name="Anthony McGill" Odds="200/1" OddsDecimal="201.00" OddsAmerican="20000" Handicap="" ID="69357774" LastUpdated="20/06/20 21:39:20" AVG="47311D13407EC5529702320355A414AE95691669" /><Participant Name="Tom Ford" Odds="200/1" OddsDecimal="201.00" OddsAmerican="20000" Handicap="" ID="69358712" LastUpdated="20/06/20 21:39:20" AVG="C4AF4E6F3E2D929CCC3DB98147A6710A5A61C87E" /><Participant Name="Xiao Guodong" Odds="200/1" OddsDecimal="201.00" OddsAmerican="20000" Handicap="" ID="69358713" LastUpdated="20/06/20 21:39:20" AVG="C784055ED56DB8B6F2CFF17B72AE2222B5491A23" /><Participant Name="Li Hang" Odds="250/1" OddsDecimal="251.00" OddsAmerican="25000" Handicap="" ID="69358302" LastUpdated="20/06/20 21:39:20" AVG="54BF90C00739C2F1C9EE8850C18B0A44A2970297" /><Participant Name="Tian Pengfei" Odds="250/1" OddsDecimal="251.00" OddsAmerican="25000" Handicap="" ID="69358711" LastUpdated="20/06/20 21:39:20" AVG="432D5256DC8F52BED4A9200FFA5758DD9CFB07CB" /><Participant Name="Mark Davis" Odds="250/1" OddsDecimal="251.00" OddsAmerican="25000" Handicap="" ID="69358429" LastUpdated="20/06/20 21:39:20" AVG="62CA1ADE6707F23DE04CB2E6F675E9473C25F71D" /><Participant Name="Scott Donaldson" Odds="250/1" OddsDecimal="251.00" OddsAmerican="25000" Handicap="" ID="69358695" LastUpdated="20/06/20 21:39:20" AVG="A61595E4E3487E975E204A0BDBDA95C2307161CE" /><Participant Name="Kurt Maflin" Odds="250/1" OddsDecimal="251.00" OddsAmerican="25000" Handicap="" ID="69358264" LastUpdated="20/06/20 21:39:20" AVG="B076AC313EEBA8142E575FADF0A0538650932A58" /><Participant Name="Robert Milkins" Odds="250/1" OddsDecimal="251.00" OddsAmerican="25000" Handicap="" ID="69358604" LastUpdated="20/06/20 21:39:20" AVG="F1A07FD5FD91C2DE23F935BC3B10A70784723CE0" /><Participant Name="Noppon Saengkham" Odds="250/1" OddsDecimal="251.00" OddsAmerican="25000" Handicap="" ID="69358577" LastUpdated="20/06/20 21:39:20" AVG="571895B9E72F36CB83CE5D72992B024CD8F1D17F" /><Participant Name="Ben Woollaston" Odds="250/1" OddsDecimal="251.00" OddsAmerican="25000" Handicap="" ID="69357828" LastUpdated="20/06/20 21:39:20" AVG="68E62A657D923A592F4FC225F5B6A39F65D92EEF" /><Participant Name="Martin O'Donnell" Odds="300/1" OddsDecimal="301.00" OddsAmerican="30000" Handicap="" ID="69358476" LastUpdated="20/06/20 21:39:20" AVG="032379CAFF10D502CB85E442CE22511482D158B5" /><Participant Name="Matthew Selt" Odds="300/1" OddsDecimal="301.00" OddsAmerican="30000" Handicap="" ID="69358493" LastUpdated="20/06/20 21:39:20" AVG="EE767C6C2E93CCEDDF51B6A4B957ED736A5F751C" /><Participant Name="Matthew Stevens" Odds="300/1" OddsDecimal="301.00" OddsAmerican="30000" Handicap="" ID="69358501" LastUpdated="20/06/20 21:39:20" AVG="A1C8D9EA2E7C7AE53C3C7D3691F3BC185CC41E52" /><Participant Name="Lyu Haotian" Odds="300/1" OddsDecimal="301.00" OddsAmerican="30000" Handicap="" ID="69358389" LastUpdated="20/06/20 21:39:20" AVG="911AAB8D19F1706683D6C67C10A0489E18CBDFF2" /><Participant Name="Lu Ning" Odds="300/1" OddsDecimal="301.00" OddsAmerican="30000" Handicap="" ID="69358358" LastUpdated="20/06/20 21:39:20" AVG="5AE40E3635A9588754E82B85EDD1C268E3D5DC7B" /><Participant Name="James Cahill" Odds="300/1" OddsDecimal="301.00" OddsAmerican="30000" Handicap="" ID="69358011" LastUpdated="20/06/20 21:39:20" AVG="5DEDBA6EAAC62B53F36DEA9BD6EDEAFCA07C84C5" /><Participant Name="Chris Wakelin" Odds="300/1" OddsDecimal="301.00" OddsAmerican="30000" Handicap="" ID="69357937" LastUpdated="20/06/20 21:39:20" AVG="5DA8B95089CCC6ED7F0362871E3B1B2EF03A4C96" /><Participant Name="Michael Holt" Odds="300/1" OddsDecimal="301.00" OddsAmerican="30000" Handicap="" ID="69358524" LastUpdated="20/06/20 21:39:20" AVG="EDA34DC4E55C7FE693174CDFB881F5DAAA72BE52" /><Participant Name="Jimmy Robertson" Odds="300/1" OddsDecimal="301.00" OddsAmerican="30000" Handicap="" ID="69358072" LastUpdated="20/06/20 21:39:20" AVG="0236D96CE36AC59A0F0DFEA8562C78EA1502CF57" /><Participant Name="Stuart Carrington" Odds="300/1" OddsDecimal="301.00" OddsAmerican="30000" Handicap="" ID="69358707" LastUpdated="20/06/20 21:39:20" AVG="D7349F9387C2DCAF586CF75C9F49CC96C437A6A1" /><Participant Name="Hossein Vafaei" Odds="300/1" OddsDecimal="301.00" OddsAmerican="30000" Handicap="" ID="69357996" LastUpdated="20/06/20 21:39:20" AVG="00247B746788E71AEF26D3699F9BD6C4D549F34A" /><Participant Name="Peter Ebdon" Odds="300/1" OddsDecimal="301.00" OddsAmerican="30000" Handicap="" ID="69358599" LastUpdated="20/06/20 21:39:20" AVG="6019547784039BD34D91B9A2F9D0C0EB5C5C660F" /><Participant Name="Mark King" Odds="300/1" OddsDecimal="301.00" OddsAmerican="30000" Handicap="" ID="69358463" LastUpdated="20/06/20 21:39:20" AVG="F4BB26163A0DF9B3E6DB97D6F213CA7F2B307E42" /><Participant Name="Luo Honghao" Odds="300/1" OddsDecimal="301.00" OddsAmerican="30000" Handicap="" ID="69358377" LastUpdated="20/06/20 21:39:20" AVG="60757ADE8BA36D367C6B6ADE6F38C747F69FC4DC" /><Participant Name="Zhang Anda" Odds="400/1" OddsDecimal="401.00" OddsAmerican="40000" Handicap="" ID="69358740" LastUpdated="20/06/20 21:39:20" AVG="64F0367450A61F1B4201F75B5D92940556FD2D0A" /><Participant Name="Liam Highfield" Odds="400/1" OddsDecimal="401.00" OddsAmerican="40000" Handicap="" ID="69358315" LastUpdated="20/06/20 21:39:20" AVG="16A0C343ED94804780547794F31E87DA784E942A" /><Participant Name="Robbie Williams" Odds="400/1" OddsDecimal="401.00" OddsAmerican="40000" Handicap="" ID="69358603" LastUpdated="20/06/20 21:39:20" AVG="6984160D67C3E474FDA1526612C2C6C7F28D4483" /><Participant Name="Andrew Higginson" Odds="400/1" OddsDecimal="401.00" OddsAmerican="40000" Handicap="" ID="69357750" LastUpdated="20/06/20 21:39:20" AVG="2725FBD1DC92D22715537AC2AC3AC93F74E13228" /><Participant Name="Daniel Wells" Odds="400/1" OddsDecimal="401.00" OddsAmerican="40000" Handicap="" ID="69357939" LastUpdated="20/06/20 21:39:20" AVG="71B65A9DFC07997AFBE03265DAF1144E6CE80B17" /><Participant Name="Mei Xiwen" Odds="400/1" OddsDecimal="401.00" OddsAmerican="40000" Handicap="" ID="69358518" LastUpdated="20/06/20 21:39:20" AVG="E693DBC549175F41166448660BBF67A2BF0B069A" /><Participant Name="Michael Georgiou" Odds="400/1" OddsDecimal="401.00" OddsAmerican="40000" Handicap="" ID="69358521" LastUpdated="20/06/20 21:39:20" AVG="434F09235D9FA83E8226C20288795D437C74477D" /><Participant Name="Sam Baird" Odds="400/1" OddsDecimal="401.00" OddsAmerican="40000" Handicap="" ID="69358676" LastUpdated="20/06/20 21:39:20" AVG="75AD45FFC987FB581FB39E22D65353C08FD59186" /><Participant Name="Akani Songsermsawad" Odds="500/1" OddsDecimal="501.00" OddsAmerican="50000" Handicap="" ID="69357699" LastUpdated="20/06/20 21:39:20" AVG="9152A734725CBB1577C4633350BC866ECD8D0D28" /><Participant Name="Dominic Dale" Odds="500/1" OddsDecimal="501.00" OddsAmerican="50000" Handicap="" ID="69357942" LastUpdated="20/06/20 21:39:20" AVG="764A0650226CEA56C5E9143DC07D09029A010EB6" /><Participant Name="Eden Sharav" Odds="500/1" OddsDecimal="501.00" OddsAmerican="50000" Handicap="" ID="69357944" LastUpdated="20/06/20 21:39:20" AVG="B698704F4DC03124AE48804AA2A3BA68AFB3C0C5" /><Participant Name="Elliot Slessor" Odds="500/1" OddsDecimal="501.00" OddsAmerican="50000" Handicap="" ID="69357955" LastUpdated="20/06/20 21:39:20" AVG="5C6576307892F4427DCF6E7505FA989CF082B4AF" /><Participant Name="Joe O'Connor" Odds="500/1" OddsDecimal="501.00" OddsAmerican="50000" Handicap="" ID="69358113" LastUpdated="20/06/20 21:39:20" AVG="8DCDA66834100D5682A0B330848AC7F5D011D573" /><Participant Name="Fergal O'Brien" Odds="500/1" OddsDecimal="501.00" OddsAmerican="50000" Handicap="" ID="69357977" LastUpdated="20/06/20 21:39:20" AVG="A607647E749BADFF840E879AF9E9F8F19C367AB3" /><Participant Name="Craig Steadman" Odds="500/1" OddsDecimal="501.00" OddsAmerican="50000" Handicap="" ID="69357938" LastUpdated="20/06/20 21:39:20" AVG="3E7E284BAE2DD211A42DD68BFD17B0A35A09FA16" /><Participant Name="Alan McManus" Odds="500/1" OddsDecimal="501.00" OddsAmerican="50000" Handicap="" ID="69357709" LastUpdated="20/06/20 21:39:20" AVG="E6043E59738E7FE51266B1F94B824F53A3B7DDF0" /><Participant Name="David Lilley" Odds="500/1" OddsDecimal="501.00" OddsAmerican="50000" Handicap="" ID="113058933" LastUpdated="20/06/20 21:39:20" AVG="F30662ADD8E826854A6DE8B6CC7874726BFBA0FF" /><Participant Name="Ken Doherty" Odds="500/1" OddsDecimal="501.00" OddsAmerican="50000" Handicap="" ID="69358243" LastUpdated="20/06/20 21:39:20" AVG="FE494A88A4E7CDF4A1C9E8AB9829DFB71FE38044" /><Participant Name="Si Jiahui" Odds="500/1" OddsDecimal="501.00" OddsAmerican="50000" Handicap="" ID="113058931" LastUpdated="20/06/20 21:39:20" AVG="F0B1565B3B376862B2AE1FD599E137CD5F4AF25F" /><Participant Name="Michael White" Odds="500/1" OddsDecimal="501.00" OddsAmerican="50000" Handicap="" ID="69358566" LastUpdated="20/06/20 21:39:20" AVG="1C6EB9DC8362F7279D5F6AE5984756DA40397F0D" /><Participant Name="Anthony Hamilton" Odds="500/1" OddsDecimal="501.00" OddsAmerican="50000" Handicap="" ID="69357757" LastUpdated="20/06/20 21:39:20" AVG="4E6ADD81334E8B8C708D27BC2F86DAB4B99DA280" /><Participant Name="Mark Joyce" Odds="500/1" OddsDecimal="501.00" OddsAmerican="50000" Handicap="" ID="69358430" LastUpdated="20/06/20 21:39:20" AVG="48085FF679DDF7D70D5E1B680082DDF317CF9348" /><Participant Name="Ian Burns" Odds="500/1" OddsDecimal="501.00" OddsAmerican="50000" Handicap="" ID="69357997" LastUpdated="20/06/20 21:39:20" AVG="DD6402EC59D849BD40D38521C369E2F68E48ED3B" /><Participant Name="Gerard Greene" Odds="750/1" OddsDecimal="751.00" OddsAmerican="75000" Handicap="" ID="69357989" LastUpdated="20/06/20 21:39:20" AVG="5AF980DCDA0D1E6D302FD541731484F27AA2C412" /><Participant Name="Alexander Ursenbacher" Odds="750/1" OddsDecimal="751.00" OddsAmerican="75000" Handicap="" ID="69357715" LastUpdated="20/06/20 21:39:20" AVG="3058242C06109165ED7661E417BCE2011190913D" /><Participant Name="Jak Jones" Odds="750/1" OddsDecimal="751.00" OddsAmerican="75000" Handicap="" ID="69358001" LastUpdated="20/06/20 21:39:20" AVG="F41EAD298B9C981D74FB236EBE4111728539BE1E" /><Participant Name="Lee Walker" Odds="750/1" OddsDecimal="751.00" OddsAmerican="75000" Handicap="" ID="69358295" LastUpdated="20/06/20 21:39:20" AVG="680AEC0B67BDAF9997B9D1576F1F16B3DC029A9B" /><Participant Name="David Grace" Odds="750/1" OddsDecimal="751.00" OddsAmerican="75000" Handicap="" ID="86265681" LastUpdated="20/06/20 21:39:20" AVG="3BEE8CB46FCE8229960C920BE60CE1CB12E86BDC" /><Participant Name="Chang Bingyu" Odds="750/1" OddsDecimal="751.00" OddsAmerican="75000" Handicap="" ID="114898106" LastUpdated="20/06/20 21:39:20" AVG="192F8D4D18DF1DE17ED573EC22D1D3E40293010C" /><Participant Name="Alfie Burden" Odds="750/1" OddsDecimal="751.00" OddsAmerican="75000" Handicap="" ID="69357718" LastUpdated="20/06/20 21:39:20" AVG="7BE9A90A2168EE1BD47BCDB4B9B6DB7D74E9A371" /><Participant Name="Mike Dunn" Odds="750/1" OddsDecimal="751.00" OddsAmerican="75000" Handicap="" ID="69358568" LastUpdated="20/06/20 21:39:20" AVG="950343AE6BA5A3316E05A9B527D1FC923A597559" /><Participant Name="John Astley" Odds="750/1" OddsDecimal="751.00" OddsAmerican="75000" Handicap="" ID="69358161" LastUpdated="20/06/20 21:39:20" AVG="68E22D6EFEA53DD1A3D76814C216BA25873513CF" /><Participant Name="Ross Bulman" Odds="750/1" OddsDecimal="751.00" OddsAmerican="75000" Handicap="" ID="678586110" LastUpdated="20/06/20 21:39:20" AVG="3BA1A1F103DE65E2D26AFC9F5D08EE403F41DFF7" /><Participant Name="Aaron Hill" Odds="750/1" OddsDecimal="751.00" OddsAmerican="75000" Handicap="" ID="678586111" LastUpdated="20/06/20 21:39:20" AVG="C2D56A5D71552FFEC26D24AFA49CA537053D6672" /><Participant Name="Duane Jones" Odds="1000/1" OddsDecimal="1001.00" OddsAmerican="100000" Handicap="" ID="69357943" LastUpdated="20/06/20 21:39:20" AVG="1BCC82F14CCFE3B0729CF715688E571452918F03" /><Participant Name="Mitchell Mann" Odds="1000/1" OddsDecimal="1001.00" OddsAmerican="100000" Handicap="" ID="113069352" LastUpdated="20/06/20 21:39:20" AVG="35D480EE0ED49AB0902BDB040469E6D8B432A4B0" /><Participant Name="Peter Lines" Odds="1000/1" OddsDecimal="1001.00" OddsAmerican="100000" Handicap="" ID="69358600" LastUpdated="20/06/20 21:39:20" AVG="0B94F55838794A200A966A241799887C3AB9FCBA" /><Participant Name="Oliver Lines" Odds="1000/1" OddsDecimal="1001.00" OddsAmerican="100000" Handicap="" ID="69358592" LastUpdated="20/06/20 21:39:20" AVG="5F63A09F91513194CA93F222E5464D352B3965E2" /><Participant Name="Xu Si" Odds="1000/1" OddsDecimal="1001.00" OddsAmerican="100000" Handicap="" ID="69358716" LastUpdated="20/06/20 21:39:20" AVG="87F08A2B6FF3065B908875C701C1B381E8B1FF35" /><Participant Name="Fraser Patrick" Odds="1500/1" OddsDecimal="1501.00" OddsAmerican="150000" Handicap="" ID="113058936" LastUpdated="20/06/20 21:39:20" AVG="231ACC11C6D167B7F1DF03C2B7E3806224E82E6D" /><Participant Name="Michael Judge" Odds="1500/1" OddsDecimal="1501.00" OddsAmerican="150000" Handicap="" ID="69358525" LastUpdated="20/06/20 21:39:20" AVG="91119FD5112898315EE70B0C350FC1F2265D5BF5" /><Participant Name="Jimmy White" Odds="1500/1" OddsDecimal="1501.00" OddsAmerican="150000" Handicap="" ID="69358097" LastUpdated="20/06/20 21:39:20" AVG="1A2F80F6DC7E62B171B55963533555391F82B563" /><Participant Name="Soheil Vahedi" Odds="1500/1" OddsDecimal="1501.00" OddsAmerican="150000" Handicap="" ID="69358702" LastUpdated="20/06/20 21:39:20" AVG="EC953EA642491E0BCFE77BF0D888F7C956123319" /><Participant Name="Nigel Bond" Odds="1500/1" OddsDecimal="1501.00" OddsAmerican="150000" Handicap="" ID="69358573" LastUpdated="20/06/20 21:39:20" AVG="A6EA35223096E2237D24316F1EDAA6F318BD461B" /><Participant Name="Rod Lawler" Odds="1500/1" OddsDecimal="1501.00" OddsAmerican="150000" Handicap="" ID="69358619" LastUpdated="20/06/20 21:39:20" AVG="90644EF8F24B20A4580DF70BE2170608DDE95DC3" /><Participant Name="Barry Pinches" Odds="2000/1" OddsDecimal="2001.00" OddsAmerican="200000" Handicap="" ID="113058915" LastUpdated="20/06/20 21:39:20" AVG="9F35CE61EF4DBA1B97CD9A285D8792F05BFDE2C4" /><Participant Name="Ashley Carty" Odds="2000/1" OddsDecimal="2001.00" OddsAmerican="200000" Handicap="" ID="69357787" LastUpdated="20/06/20 21:39:20" AVG="20C2817F7FE82A2A0B99D3E90DA43EF220A6FD79" /><Participant Name="Hammad Miah" Odds="2000/1" OddsDecimal="2001.00" OddsAmerican="200000" Handicap="" ID="69357991" LastUpdated="20/06/20 21:39:20" AVG="E9A32941A562F3CD871736B9008EBF0A44C688B0" /><Participant Name="Steve Mifsud" Odds="2000/1" OddsDecimal="2001.00" OddsAmerican="200000" Handicap="" ID="115198541" LastUpdated="20/06/20 21:39:20" AVG="A870AAF8334090C0C34FE4F2BCC9EECB4FB1653A" /><Participant Name="Igor Figueiredo" Odds="2000/1" OddsDecimal="2001.00" OddsAmerican="200000" Handicap="" ID="115198546" LastUpdated="20/06/20 21:39:20" AVG="99CBA7A991CFE87F0808EF5B687886FFAC275D20" /><Participant Name="Jackson Page" Odds="2000/1" OddsDecimal="2001.00" OddsAmerican="200000" Handicap="" ID="115198838" LastUpdated="20/06/20 21:39:20" AVG="346B875724729DC4F7D9FB40337EAB9F5FF6F2F2" /><Participant Name="Brandon Sargeant" Odds="2000/1" OddsDecimal="2001.00" OddsAmerican="200000" Handicap="" ID="86265695" LastUpdated="20/06/20 21:39:20" AVG="086B1CCA78AA278DB578431FE245055EE993386B" /><Participant Name="Andy Hicks" Odds="2000/1" OddsDecimal="2001.00" OddsAmerican="200000" Handicap="" ID="113058922" LastUpdated="20/06/20 21:39:20" AVG="5F925FB6C7EB583EEC9904581920932F08EB23B1" /><Participant Name="Alex Borg" Odds="2000/1" OddsDecimal="2001.00" OddsAmerican="200000" Handicap="" ID="113058926" LastUpdated="20/06/20 21:39:20" AVG="0645F85941583DABEA64AD08810701C3D921B15C" /><Participant Name="Jamie O'Neill" Odds="2000/1" OddsDecimal="2001.00" OddsAmerican="200000" Handicap="" ID="113058928" LastUpdated="20/06/20 21:39:20" AVG="A47C32D19E763BBEE983ACDBC65E45325B7A6FC3" /><Participant Name="Adam Stefanow" Odds="2000/1" OddsDecimal="2001.00" OddsAmerican="200000" Handicap="" ID="69357693" LastUpdated="20/06/20 21:39:20" AVG="9B745A3D7BE23F96494DF70D05C1184856317C31" /><Participant Name="Riley Parsons" Odds="2000/1" OddsDecimal="2001.00" OddsAmerican="200000" Handicap="" ID="113058934" LastUpdated="20/06/20 21:39:20" AVG="C1EC26E8758052430A17703631BA85415D28CCCF" /><Participant Name="Louis Heathcote" Odds="2000/1" OddsDecimal="2001.00" OddsAmerican="200000" Handicap="" ID="113058935" LastUpdated="20/06/20 21:39:20" AVG="7FC048ADCBA742562034D5D34F363192106C21BD" /><Participant Name="Zhang Jiankang" Odds="2000/1" OddsDecimal="2001.00" OddsAmerican="200000" Handicap="" ID="69358741" LastUpdated="20/06/20 21:39:20" AVG="59655B6E942AD094871A33159E0FC23E2D4DD78F" /><Participant Name="Jamie Clark" Odds="2000/1" OddsDecimal="2001.00" OddsAmerican="200000" Handicap="" ID="69358031" LastUpdated="20/06/20 21:39:20" AVG="06B3C0508FF1DBDBF90A11DFA466782ECD7DB89D" /><Participant Name="Kacper Filipiak" Odds="2000/1" OddsDecimal="2001.00" OddsAmerican="200000" Handicap="" ID="114898112" LastUpdated="20/06/20 21:39:20" AVG="A6A675E27AA0937B88C17358213DD4EA51667CF0" /><Participant Name="Billy Joe Castle" Odds="2000/1" OddsDecimal="2001.00" OddsAmerican="200000" Handicap="" ID="69357838" LastUpdated="20/06/20 21:39:20" AVG="294EA13793F76DC4A31604DE75B4EB3EB25556E9" /><Participant Name="Chen Zifan" Odds="2000/1" OddsDecimal="2001.00" OddsAmerican="200000" Handicap="" ID="69357892" LastUpdated="20/06/20 21:39:20" AVG="5159DA6CA0DDBBCEF85B183AAB6DA3622100646E" /><Participant Name="James Wattana" Odds="2000/1" OddsDecimal="2001.00" OddsAmerican="200000" Handicap="" ID="69358021" LastUpdated="20/06/20 21:39:20" AVG="DABCAB44EDC70D5ECFE9FD4867095074FF5100CA" /><Participant Name="Harvey Chandler" Odds="2000/1" OddsDecimal="2001.00" OddsAmerican="200000" Handicap="" ID="69357995" LastUpdated="20/06/20 21:39:20" AVG="FC97D9206936D0F7820D842D2F269473FC94CBE4" /><Participant Name="Thor Chuan Leong" Odds="2000/1" OddsDecimal="2001.00" OddsAmerican="200000" Handicap="" ID="69358710" LastUpdated="20/06/20 21:39:20" AVG="9516AE08A3FAC831FBFCBA49CA02B4C5EA04F204" /><Participant Name="Jordan Brown" Odds="2000/1" OddsDecimal="2001.00" OddsAmerican="200000" Handicap="" ID="69358185" LastUpdated="20/06/20 21:39:20" AVG="A55D9B4A0D8AF1EC34D5B9EBAA6F8CE170E6FEE3" /><Participant Name="Simon Lichtenberg" Odds="2500/1" OddsDecimal="2501.00" OddsAmerican="250000" Handicap="" ID="69358699" LastUpdated="20/06/20 21:39:20" AVG="798FD1828BFE990332A3287332505746079793FE" /><Participant Name="Andy Lee" Odds="2500/1" OddsDecimal="2501.00" OddsAmerican="250000" Handicap="" ID="69357754" LastUpdated="20/06/20 21:39:20" AVG="2528BC1BFD8D1D1336982E9A873482F3025B6C17" /><Participant Name="Kishan Hirani" Odds="2500/1" OddsDecimal="2501.00" OddsAmerican="250000" Handicap="" ID="69358256" LastUpdated="20/06/20 21:39:20" AVG="923C4D03A000276BD71F1DBDBBFCB1BCB1A98D9A" /><Participant Name="Chen Feilong" Odds="2500/1" OddsDecimal="2501.00" OddsAmerican="250000" Handicap="" ID="69357865" LastUpdated="20/06/20 21:39:20" AVG="F36C2861D60C6CBDF64A362D68521695ADF5633C" /><Participant Name="Fan Zhengyi" Odds="2500/1" OddsDecimal="2501.00" OddsAmerican="250000" Handicap="" ID="69357966" LastUpdated="20/06/20 21:39:20" AVG="617FFEC11B01E852E1E94A4E49FCB0F7B51F70A3" /><Participant Name="Peifan Lei" Odds="2500/1" OddsDecimal="2501.00" OddsAmerican="250000" Handicap="" ID="113058929" LastUpdated="20/06/20 21:39:20" AVG="547EB7475E939D1ED0C80F1477EA4D2A973886BB" /><Participant Name="Ng On Yee" Odds="2500/1" OddsDecimal="2501.00" OddsAmerican="250000" Handicap="" ID="86265725" LastUpdated="20/06/20 21:39:20" AVG="F1B64119786279CB718E61217D17A8BA659FDB7B" /><Participant Name="Reanne Evans" Odds="2500/1" OddsDecimal="2501.00" OddsAmerican="250000" Handicap="" ID="86265707" LastUpdated="20/06/20 21:39:20" AVG="B020DD5AEAF6B95830D4B54CCD6902C108EEF483" /><Participant Name="Bai Langning" Odds="2500/1" OddsDecimal="2501.00" OddsAmerican="250000" Handicap="" ID="114898099" LastUpdated="20/06/20 21:39:20" AVG="CB56368D9310B69ADF57F9385C1766117D70F77B" /><Participant Name="Sean Maddocks" Odds="5000/1" OddsDecimal="5001.00" OddsAmerican="500000" Handicap="" ID="835035378" LastUpdated="22/06/20 11:53:02" AVG="C66B11E4FC00F86D9F22204DED06AC43605B1682" /></Market></Event></EventGroup><EventGroup name="Tour Championship 2020" ID="20692572"><Event Name="Tour Championship 2020" ID="306881636"><Market Name="To Win Outright" ID="82" FID="87432530" StartTime="26/06/20 19:00:00" EventComment="" PlaceTerms="1, 1/1"><Participant Name="Mark Selby" Odds="6/4" OddsDecimal="2.50" OddsAmerican="150" Handicap="" ID="676908790" LastUpdated="24/06/20 22:40:44" AVG="45BDE3FC60C3EAC257A74ADFA45B1E9628830F88" /><Participant Name="Stephen Maguire" Odds="13/8" OddsDecimal="2.62" OddsAmerican="162" Handicap="" ID="813287277" LastUpdated="24/06/20 22:40:44" AVG="EDF296C7547724D86471AB011284EFAC90B22808" /><Participant Name="Mark Allen" Odds="5/2" OddsDecimal="3.50" OddsAmerican="250" Handicap="" ID="676908793" LastUpdated="24/06/20 22:40:44" AVG="87EE52888D3E55918F5216FE15CA73BE12A9545B" /></Market></Event></EventGroup></Sport>