<?xml version="1.0" encoding="utf-8"?><Sport Name="Darts" PageTitle="Filtered applied. MarketID: 150135 " TimeStamp="25/06/20 13:17:03"><EventGroup name="Icons of Darts Live League 2020" ID="20694173"><Event Name="Paul Nicholson vs Stephen Burton" ID="-2144406749"><Market Name="Final Leg Winning Double - Colour" ID="150135" FID="90432445" StartTime="25/06/20 15:20:00" EventComment="" PlaceTerms="1, 1/1"><Participant Name="Red" Odds="2/5" OddsDecimal="1.40" OddsAmerican="-250" Handicap="" ID="838079932" LastUpdated="23/06/20 17:22:52" AVG="4D91F96FED703797C7F42F27AF4E1F70080E6CFF" /><Participant Name="Green" Odds="7/4" OddsDecimal="2.75" OddsAmerican="175" Handicap="" ID="838079918" LastUpdated="23/06/20 17:22:52" AVG="2E03486573E1E61A66B8D835FE86343761BEE1D7" /></Market></Event><Event Name="Keane Barry vs Martin Adams" ID="-1922564706"><Market Name="Final Leg Winning Double - Colour" ID="150135" FID="90432840" StartTime="26/06/20 16:35:00" EventComment="" PlaceTerms="1, 1/1"><Participant Name="Red" Odds="4/9" OddsDecimal="1.44" OddsAmerican="-225" Handicap="" ID="840330354" LastUpdated="24/06/20 17:43:46" AVG="A7DFAA3959B0B3751ABB72D7A2036207A7AE9C15" /><Participant Name="Green" Odds="13/8" OddsDecimal="2.62" OddsAmerican="162" Handicap="" ID="840330353" LastUpdated="24/06/20 17:43:46" AVG="12286DB029B012045CBB9F3C5B1F107C7A68A285" /></Market></Event><Event Name="Ritchie Edhouse vs Andy Jenkins" ID="-1863621494"><Market Name="Final Leg Winning Double - Colour" ID="150135" FID="90432726" StartTime="26/06/20 11:20:00" EventComment="" PlaceTerms="1, 1/1"><Participant Name="Red" Odds="4/9" OddsDecimal="1.44" OddsAmerican="-225" Handicap="" ID="840292272" LastUpdated="24/06/20 17:22:48" AVG="7C0AF5BA351ADD42A7B4AE09FE937C34250E43A1" /><Participant Name="Green" Odds="13/8" OddsDecimal="2.62" OddsAmerican="162" Handicap="" ID="840292271" LastUpdated="24/06/20 17:22:48" AVG="468BF956BBCD8DB1797A9F0B1E9A458CCE142DAE" /></Market></Event><Event Name="Keane Barry vs Fallon Sherrock" ID="-1827010740"><Market Name="Final Leg Winning Double - Colour" ID="150135" FID="90432794" StartTime="26/06/20 14:30:00" EventComment="" PlaceTerms="1, 1/1"><Participant Name="Red" Odds="4/9" OddsDecimal="1.44" OddsAmerican="-225" Handicap="" ID="840329826" LastUpdated="24/06/20 17:38:47" AVG="FF1824D967AC2980C11109A1A3CEFA83B1BF61F5" /><Participant Name="Green" Odds="13/8" OddsDecimal="2.62" OddsAmerican="162" Handicap="" ID="840329823" LastUpdated="24/06/20 17:38:47" AVG="17CB7A9FE473AAAA62DDED1751FF8A2E809CD36B" /></Market></Event><Event Name="Mark Webster vs Paul Nicholson" ID="-1765996007"><Market Name="Final Leg Winning Double - Colour" ID="150135" FID="90432475" StartTime="25/06/20 16:35:00" EventComment="" PlaceTerms="1, 1/1"><Participant Name="Red" Odds="4/11" OddsDecimal="1.36" OddsAmerican="-275" Handicap="" ID="838080591" LastUpdated="23/06/20 17:27:19" AVG="6543656925D47834EF73026C8EF71036AB7E9F88" /><Participant Name="Green" Odds="2/1" OddsDecimal="3.00" OddsAmerican="200" Handicap="" ID="838080589" LastUpdated="23/06/20 17:27:19" AVG="94C32D99E70C32505239C5B78C5902C49CE21A17" /></Market></Event><Event Name="Mark Webster vs Keane Barry" ID="-1384020679"><Market Name="Final Leg Winning Double - Colour" ID="150135" FID="90432425" StartTime="25/06/20 14:30:00" EventComment="" PlaceTerms="1, 1/1"><Participant Name="Red" Odds="4/11" OddsDecimal="1.36" OddsAmerican="-275" Handicap="" ID="838161760" LastUpdated="23/06/20 18:05:04" AVG="0643D3FE6504E71742E48E8BB0417A18D2C0F3AE" /><Participant Name="Green" Odds="2/1" OddsDecimal="3.00" OddsAmerican="200" Handicap="" ID="838161757" LastUpdated="23/06/20 18:05:04" AVG="08C2678D9F7D445401AE0E1123D97CBDFC684537" /></Market></Event><Event Name="Stephen Burton vs Michael Warburton" ID="-1159596945"><Market Name="Final Leg Winning Double - Colour" ID="150135" FID="90432423" StartTime="25/06/20 14:05:00" EventComment="" PlaceTerms="1, 1/1"><Participant Name="Red" Odds="2/5" OddsDecimal="1.40" OddsAmerican="-250" Handicap="" ID="838079554" LastUpdated="23/06/20 17:20:11" AVG="B7679BB8F18D872BE793BAF06893D23C194581DC" /><Participant Name="Green" Odds="7/4" OddsDecimal="2.75" OddsAmerican="175" Handicap="" ID="838079553" LastUpdated="23/06/20 17:20:11" AVG="B0E32BB78ADD662D706172E77D6F3EBA309AAC90" /></Market></Event><Event Name="Michael Warburton vs Mark Webster" ID="-1073929703"><Market Name="Final Leg Winning Double - Colour" ID="150135" FID="90432448" StartTime="25/06/20 15:45:00" EventComment="" PlaceTerms="1, 1/1"><Participant Name="Red" Odds="4/11" OddsDecimal="1.36" OddsAmerican="-275" Handicap="" ID="838080252" LastUpdated="23/06/20 17:24:15" AVG="BB3C9826EB5CF0984A87192356E3EFF9F12425D5" /><Participant Name="Green" Odds="2/1" OddsDecimal="3.00" OddsAmerican="200" Handicap="" ID="838080245" LastUpdated="23/06/20 17:24:15" AVG="D776A0109C1A23D912AD56FB4A9D07041ACF40CE" /></Market></Event><Event Name="Ritchie Edhouse vs Keane Barry" ID="-1067255965"><Market Name="Final Leg Winning Double - Colour" ID="150135" FID="90432777" StartTime="26/06/20 13:40:00" EventComment="" PlaceTerms="1, 1/1"><Participant Name="Red" Odds="4/9" OddsDecimal="1.44" OddsAmerican="-225" Handicap="" ID="840293084" LastUpdated="24/06/20 17:32:36" AVG="8362B3DE625E512D8A763432AA0DA518DFCA057C" /><Participant Name="Green" Odds="13/8" OddsDecimal="2.62" OddsAmerican="162" Handicap="" ID="840293078" LastUpdated="24/06/20 17:32:36" AVG="3B6301CEE7FB0B8874DEF75FB134A5251BB0A40D" /></Market></Event><Event Name="Scott Mitchell vs Mark Webster" ID="-666931149"><Market Name="Final Leg Winning Double - Colour" ID="150135" FID="90432409" StartTime="25/06/20 13:40:00" EventComment="" PlaceTerms="1, 1/1"><Participant Name="Red" Odds="1/3" OddsDecimal="1.33" OddsAmerican="-300" Handicap="" ID="838049328" LastUpdated="23/06/20 17:16:09" AVG="9FB802419AEDB9B5A167B0EF867B6BAF783A4586" /><Participant Name="Green" Odds="9/4" OddsDecimal="3.25" OddsAmerican="225" Handicap="" ID="838049326" LastUpdated="23/06/20 17:16:09" AVG="11E10BB874BC0945412851C8674A5804669867B5" /></Market></Event><Event Name="Keane Barry vs Andy Jenkins" ID="-363650974"><Market Name="Final Leg Winning Double - Colour" ID="150135" FID="90432744" StartTime="26/06/20 12:35:00" EventComment="" PlaceTerms="1, 1/1"><Participant Name="Red" Odds="4/9" OddsDecimal="1.44" OddsAmerican="-225" Handicap="" ID="840292651" LastUpdated="24/06/20 17:30:33" AVG="21CC5E8E1BB55FF6D82ED91F9210B45A037365F9" /><Participant Name="Green" Odds="13/8" OddsDecimal="2.62" OddsAmerican="162" Handicap="" ID="840292650" LastUpdated="24/06/20 17:30:33" AVG="7B721A300EAD4338A19F42112D58291D66E1BD27" /></Market></Event><Event Name="Andy Jenkins vs Jarred Cole" ID="-183630181"><Market Name="Final Leg Winning Double - Colour" ID="150135" FID="90432781" StartTime="26/06/20 14:05:00" EventComment="" PlaceTerms="1, 1/1"><Participant Name="Red" Odds="4/9" OddsDecimal="1.44" OddsAmerican="-225" Handicap="" ID="840293394" LastUpdated="24/06/20 17:33:30" AVG="2C9E498AFBF116A4105ADCEA48C92CFE0A959D62" /><Participant Name="Green" Odds="13/8" OddsDecimal="2.62" OddsAmerican="162" Handicap="" ID="840293391" LastUpdated="24/06/20 17:33:30" AVG="3DEBA88BCA9515E4301E65CB3EE56C65ADF34BE7" /></Market></Event><Event Name="Fallon Sherrock vs Martin Adams" ID="-44225258"><Market Name="Final Leg Winning Double - Colour" ID="150135" FID="90432761" StartTime="26/06/20 13:00:00" EventComment="" PlaceTerms="1, 1/1"><Participant Name="Red" Odds="4/9" OddsDecimal="1.44" OddsAmerican="-225" Handicap="" ID="840292948" LastUpdated="24/06/20 17:31:29" AVG="5BF9FA884B5C074533FFFEFE6D01D306137FEE4E" /><Participant Name="Green" Odds="13/8" OddsDecimal="2.62" OddsAmerican="162" Handicap="" ID="840292944" LastUpdated="24/06/20 17:31:29" AVG="4DE04C6033DB61839858651FC8C6137E726EE5A3" /></Market></Event><Event Name="Andy Jenkins vs Fallon Sherrock" ID="187301429"><Market Name="Final Leg Winning Double - Colour" ID="150135" FID="90432725" StartTime="26/06/20 10:55:00" EventComment="" PlaceTerms="1, 1/1"><Participant Name="Red" Odds="4/9" OddsDecimal="1.44" OddsAmerican="-225" Handicap="" ID="840292164" LastUpdated="24/06/20 17:22:08" AVG="BAD6770C5B782C48D3D0FBC1B64293312419AF75" /><Participant Name="Green" Odds="13/8" OddsDecimal="2.62" OddsAmerican="162" Handicap="" ID="840292163" LastUpdated="24/06/20 17:22:08" AVG="AAB9B05707949D77428B4593325561B0304D2B16" /></Market></Event><Event Name="Jarred Cole vs Keane Barry" ID="326278645"><Market Name="Final Leg Winning Double - Colour" ID="150135" FID="90432821" StartTime="26/06/20 15:45:00" EventComment="" PlaceTerms="1, 1/1"><Participant Name="Red" Odds="4/9" OddsDecimal="1.44" OddsAmerican="-225" Handicap="" ID="840330128" LastUpdated="24/06/20 17:42:55" AVG="A2CE874DBBC6F1BEAF0AACA3AF23468EF555718A" /><Participant Name="Green" Odds="13/8" OddsDecimal="2.62" OddsAmerican="162" Handicap="" ID="840330127" LastUpdated="24/06/20 17:42:55" AVG="93C32EA14B745B75B8C08BFF243867DACDD9433E" /></Market></Event><Event Name="Martin Adams vs Andy Jenkins" ID="452886177"><Market Name="Final Leg Winning Double - Colour" ID="150135" FID="90432813" StartTime="26/06/20 15:20:00" EventComment="" PlaceTerms="1, 1/1"><Participant Name="Red" Odds="4/9" OddsDecimal="1.44" OddsAmerican="-225" Handicap="" ID="840330235" LastUpdated="24/06/20 17:41:57" AVG="9B040570C17E30C9FE05053CBAEFA7F77FB9D43D" /><Participant Name="Green" Odds="13/8" OddsDecimal="2.62" OddsAmerican="162" Handicap="" ID="840330234" LastUpdated="24/06/20 17:41:57" AVG="6DF4091316E539874F7AAF34397E05AC3F471C55" /></Market></Event><Event Name="Martin Adams vs Jarred Cole" ID="863849284"><Market Name="Final Leg Winning Double - Colour" ID="150135" FID="90501578" StartTime="26/06/20 16:10:00" EventComment="" PlaceTerms="1, 1/1"><Participant Name="Red" Odds="4/9" OddsDecimal="1.44" OddsAmerican="-225" Handicap="" ID="840348551" LastUpdated="24/06/20 17:46:32" AVG="6EE711E05A9E1627471AFA91A855C88D1BEB27DD" /><Participant Name="Green" Odds="13/8" OddsDecimal="2.62" OddsAmerican="162" Handicap="" ID="840348546" LastUpdated="24/06/20 17:46:32" AVG="EF15CA112B80DB2CE9023CEA115A11587594EB30" /></Market></Event><Event Name="Fallon Sherrock vs Ritchie Edhouse" ID="881857583"><Market Name="Final Leg Winning Double - Colour" ID="150135" FID="90432717" StartTime="26/06/20 10:30:00" EventComment="" PlaceTerms="1, 1/1"><Participant Name="Red" Odds="4/9" OddsDecimal="1.44" OddsAmerican="-225" Handicap="" ID="840292068" LastUpdated="24/06/20 17:20:33" AVG="189919F28D0FAA193D6EB4246A0BBA23A0072027" /><Participant Name="Green" Odds="13/8" OddsDecimal="2.62" OddsAmerican="162" Handicap="" ID="840292067" LastUpdated="24/06/20 17:20:33" AVG="111C704F8C1CD9FF894A4BB19837D3203DD11200" /></Market></Event><Event Name="Martin Adams vs Ritchie Edhouse" ID="1282714662"><Market Name="Final Leg Winning Double - Colour" ID="150135" FID="90432743" StartTime="26/06/20 12:10:00" EventComment="" PlaceTerms="1, 1/1"><Participant Name="Red" Odds="4/9" OddsDecimal="1.44" OddsAmerican="-225" Handicap="" ID="840292494" LastUpdated="24/06/20 17:29:03" AVG="F409AA07C2D1068986202E798CB90E9C0D13FC1B" /><Participant Name="Green" Odds="13/8" OddsDecimal="2.62" OddsAmerican="162" Handicap="" ID="840292491" LastUpdated="24/06/20 17:29:03" AVG="481DF97BD5A0DC43B87D34F6D4894171A461E86E" /></Market></Event><Event Name="Paul Nicholson vs Michael Warburton" ID="1601688137"><Market Name="Final Leg Winning Double - Colour" ID="150135" FID="90432466" StartTime="25/06/20 16:10:00" EventComment="" PlaceTerms="1, 1/1"><Participant Name="Red" Odds="4/9" OddsDecimal="1.44" OddsAmerican="-225" Handicap="" ID="838080389" LastUpdated="23/06/20 17:25:22" AVG="267A2FCE404F9EC49073EFE948CC018A23CC37B3" /><Participant Name="Green" Odds="13/8" OddsDecimal="2.62" OddsAmerican="162" Handicap="" ID="838080386" LastUpdated="23/06/20 17:25:22" AVG="DEC1FA7F57A7DBCF9291BFC785D7D5A0873CEAA8" /></Market></Event><Event Name="Michael Warburton vs Scott Mitchell" ID="1740467234"><Market Name="Final Leg Winning Double - Colour" ID="150135" FID="90432434" StartTime="25/06/20 14:55:00" EventComment="" PlaceTerms="1, 1/1"><Participant Name="Red" Odds="2/5" OddsDecimal="1.40" OddsAmerican="-250" Handicap="" ID="838079693" LastUpdated="23/06/20 17:21:29" AVG="9112376947D07F644B6061C1BC8D1B6061F25FFA" /><Participant Name="Green" Odds="7/4" OddsDecimal="2.75" OddsAmerican="175" Handicap="" ID="838079691" LastUpdated="23/06/20 17:21:29" AVG="6F44C7B49FC7B65153CA6949E672F35BC2370125" /></Market></Event><Event Name="Jarred Cole vs Ritchie Edhouse" ID="2000734103"><Market Name="Final Leg Winning Double - Colour" ID="150135" FID="90432803" StartTime="26/06/20 14:55:00" EventComment="" PlaceTerms="1, 1/1"><Participant Name="Red" Odds="4/9" OddsDecimal="1.44" OddsAmerican="-225" Handicap="" ID="840329963" LastUpdated="24/06/20 17:41:03" AVG="E09AEFE76002CE7CFA6672E99E281CE17D5497D6" /><Participant Name="Green" Odds="13/8" OddsDecimal="2.62" OddsAmerican="162" Handicap="" ID="840329959" LastUpdated="24/06/20 17:41:03" AVG="4618055AAC40B42C938BAB2596BB3CF35039391E" /></Market></Event><Event Name="Jarred Cole vs Fallon Sherrock" ID="2109887479"><Market Name="Final Leg Winning Double - Colour" ID="150135" FID="90432742" StartTime="26/06/20 11:45:00" EventComment="" PlaceTerms="1, 1/1"><Participant Name="Red" Odds="4/9" OddsDecimal="1.44" OddsAmerican="-225" Handicap="" ID="840292487" LastUpdated="24/06/20 17:24:49" AVG="781A34E18A27A03F2BC071683D3968F0F6AE0A51" /><Participant Name="Green" Odds="13/8" OddsDecimal="2.62" OddsAmerican="162" Handicap="" ID="840292485" LastUpdated="24/06/20 17:24:49" AVG="0F378EB148CE4858EB8404C390D73C37997AC125" /></Market></Event></EventGroup></Sport>