[{"Key":"2550965664","Value":{"LiveHistory":null,"IsLive":false,"StartDate":"2020-09-17T11:00:00Z","Participants":[{"Id":14008688,"IsHome":false,"LocalizedNames":{"LocalizedValues":[{"CountryCode":"-1","LanguageCode":"-1","Value":"Brooks Koepka"}],"ReferenceId":-1},"LocalizedShortNames":{"LocalizedValues":[{"CountryCode":"-1","LanguageCode":"-1","Value":"BKo"}],"ReferenceId":0}},{"Id":14008689,"IsHome":false,"LocalizedNames":{"LocalizedValues":[{"CountryCode":"-1","LanguageCode":"-1","Value":"Rory McIlroy"}],"ReferenceId":-1},"LocalizedShortNames":{"LocalizedValues":[{"CountryCode":"-1","LanguageCode":"-1","Value":"RMc"}],"ReferenceId":0}},{"Id":14008690,"IsHome":false,"LocalizedNames":{"LocalizedValues":[{"CountryCode":"-1","LanguageCode":"-1","Value":"Dustin Johnson"}],"ReferenceId":-1},"LocalizedShortNames":{"LocalizedValues":[{"CountryCode":"-1","LanguageCode":"-1","Value":"DJo"}],"ReferenceId":0}},{"Id":14008691,"IsHome":false,"LocalizedNames":{"LocalizedValues":[{"CountryCode":"-1","LanguageCode":"-1","Value":"Tiger Woods"}],"ReferenceId":-1},"LocalizedShortNames":{"LocalizedValues":[{"CountryCode":"-1","LanguageCode":"-1","Value":"TWo"}],"ReferenceId":0}},{"Id":14008692,"IsHome":false,"LocalizedNames":{"LocalizedValues":[{"CountryCode":"-1","LanguageCode":"-1","Value":"Jon Rahm"}],"ReferenceId":-1},"LocalizedShortNames":{"LocalizedValues":[{"CountryCode":"-1","LanguageCode":"-1","Value":"JRa"}],"ReferenceId":0}},{"Id":14008693,"IsHome":false,"LocalizedNames":{"LocalizedValues":[{"CountryCode":"-1","LanguageCode":"-1","Value":"Justin Rose"}],"ReferenceId":-1},"LocalizedShortNames":{"LocalizedValues":[{"CountryCode":"-1","LanguageCode":"-1","Value":"JRo"}],"ReferenceId":0}},{"Id":14008694,"IsHome":false,"LocalizedNames":{"LocalizedValues":[{"CountryCode":"-1","LanguageCode":"-1","Value":"Jordan Spieth"}],"ReferenceId":-1},"LocalizedShortNames":{"LocalizedValues":[{"CountryCode":"-1","LanguageCode":"-1","Value":"JSp"}],"ReferenceId":0}},{"Id":14008695,"IsHome":false,"LocalizedNames":{"LocalizedValues":[{"CountryCode":"-1","LanguageCode":"-1","Value":"Justin Thomas"}],"ReferenceId":-1},"LocalizedShortNames":{"LocalizedValues":[{"CountryCode":"-1","LanguageCode":"-1","Value":"JTh"}],"ReferenceId":0}},{"Id":14008696,"IsHome":false,"LocalizedNames":{"LocalizedValues":[{"CountryCode":"-1","LanguageCode":"-1","Value":"Rickie Fowler"}],"ReferenceId":-1},"LocalizedShortNames":{"LocalizedValues":[{"CountryCode":"-1","LanguageCode":"-1","Value":"RFo"}],"ReferenceId":0}},{"Id":14008697,"IsHome":false,"LocalizedNames":{"LocalizedValues":[{"CountryCode":"-1","LanguageCode":"-1","Value":"Xander Schauffele"}],"ReferenceId":-1},"LocalizedShortNames":{"LocalizedValues":[{"CountryCode":"-1","LanguageCode":"-1","Value":"XSc"}],"ReferenceId":0}},{"Id":14008698,"IsHome":false,"LocalizedNames":{"LocalizedValues":[{"CountryCode":"-1","LanguageCode":"-1","Value":"Patrick Cantlay"}],"ReferenceId":-1},"LocalizedShortNames":{"LocalizedValues":[{"CountryCode":"-1","LanguageCode":"-1","Value":"PCa"}],"ReferenceId":0}},{"Id":14008699,"IsHome":false,"LocalizedNames":{"LocalizedValues":[{"CountryCode":"-1","LanguageCode":"-1","Value":"Jason Day"}],"ReferenceId":-1},"LocalizedShortNames":{"LocalizedValues":[{"CountryCode":"-1","LanguageCode":"-1","Value":"JDa"}],"ReferenceId":0}},{"Id":14008700,"IsHome":false,"LocalizedNames":{"LocalizedValues":[{"CountryCode":"-1","LanguageCode":"-1","Value":"Francesco Molinari"}],"ReferenceId":-1},"LocalizedShortNames":{"LocalizedValues":[{"CountryCode":"-1","LanguageCode":"-1","Value":"FMo"}],"ReferenceId":0}},{"Id":14008701,"IsHome":false,"LocalizedNames":{"LocalizedValues":[{"CountryCode":"-1","LanguageCode":"-1","Value":"Tommy Fleetwood"}],"ReferenceId":-1},"LocalizedShortNames":{"LocalizedValues":[{"CountryCode":"-1","LanguageCode":"-1","Value":"TFl"}],"ReferenceId":0}},{"Id":14008702,"IsHome":false,"LocalizedNames":{"LocalizedValues":[{"CountryCode":"-1","LanguageCode":"-1","Value":"Hideki Matsuyama"}],"ReferenceId":-1},"LocalizedShortNames":{"LocalizedValues":[{"CountryCode":"-1","LanguageCode":"-1","Value":"HMa"}],"ReferenceId":0}},{"Id":14008703,"IsHome":false,"LocalizedNames":{"LocalizedValues":[{"CountryCode":"-1","LanguageCode":"-1","Value":"Bryson DeChambeau"}],"ReferenceId":-1},"LocalizedShortNames":{"LocalizedValues":[{"CountryCode":"-1","LanguageCode":"-1","Value":"BDe"}],"ReferenceId":0}},{"Id":14008704,"IsHome":false,"LocalizedNames":{"LocalizedValues":[{"CountryCode":"-1","LanguageCode":"-1","Value":"Adam Scott"}],"ReferenceId":-1},"LocalizedShortNames":{"LocalizedValues":[{"CountryCode":"-1","LanguageCode":"-1","Value":"ASc"}],"ReferenceId":0}},{"Id":14008705,"IsHome":false,"LocalizedNames":{"LocalizedValues":[{"CountryCode":"-1","LanguageCode":"-1","Value":"Tony Finau"}],"ReferenceId":-1},"LocalizedShortNames":{"LocalizedValues":[{"CountryCode":"-1","LanguageCode":"-1","Value":"TFi"}],"ReferenceId":0}},{"Id":14008706,"IsHome":false,"LocalizedNames":{"LocalizedValues":[{"CountryCode":"-1","LanguageCode":"-1","Value":"Paul Casey"}],"ReferenceId":-1},"LocalizedShortNames":{"LocalizedValues":[{"CountryCode":"-1","LanguageCode":"-1","Value":"PCa"}],"ReferenceId":0}},{"Id":14008707,"IsHome":false,"LocalizedNames":{"LocalizedValues":[{"CountryCode":"-1","LanguageCode":"-1","Value":"Patrick Reed"}],"ReferenceId":-1},"LocalizedShortNames":{"LocalizedValues":[{"CountryCode":"-1","LanguageCode":"-1","Value":"PRe"}],"ReferenceId":0}},{"Id":14008708,"IsHome":false,"LocalizedNames":{"LocalizedValues":[{"CountryCode":"-1","LanguageCode":"-1","Value":"Henrik Stenson"}],"ReferenceId":-1},"LocalizedShortNames":{"LocalizedValues":[{"CountryCode":"-1","LanguageCode":"-1","Value":"HSt"}],"ReferenceId":0}},{"Id":14008709,"IsHome":false,"LocalizedNames":{"LocalizedValues":[{"CountryCode":"-1","LanguageCode":"-1","Value":"Matt Kuchar"}],"ReferenceId":-1},"LocalizedShortNames":{"LocalizedValues":[{"CountryCode":"-1","LanguageCode":"-1","Value":"MKu"}],"ReferenceId":0}},{"Id":14008710,"IsHome":false,"LocalizedNames":{"LocalizedValues":[{"CountryCode":"-1","LanguageCode":"-1","Value":"Sergio García"}],"ReferenceId":-1},"LocalizedShortNames":{"LocalizedValues":[{"CountryCode":"-1","LanguageCode":"-1","Value":"SGa"}],"ReferenceId":0}},{"Id":14008711,"IsHome":false,"LocalizedNames":{"LocalizedValues":[{"CountryCode":"-1","LanguageCode":"-1","Value":"Phil Mickelson"}],"ReferenceId":-1},"LocalizedShortNames":{"LocalizedValues":[{"CountryCode":"-1","LanguageCode":"-1","Value":"PMi"}],"ReferenceId":0}},{"Id":14008712,"IsHome":false,"LocalizedNames":{"LocalizedValues":[{"CountryCode":"-1","LanguageCode":"-1","Value":"Louis Oosthuizen"}],"ReferenceId":-1},"LocalizedShortNames":{"LocalizedValues":[{"CountryCode":"-1","LanguageCode":"-1","Value":"LOo"}],"ReferenceId":0}},{"Id":14008713,"IsHome":false,"LocalizedNames":{"LocalizedValues":[{"CountryCode":"-1","LanguageCode":"-1","Value":"Gary Woodland"}],"ReferenceId":-1},"LocalizedShortNames":{"LocalizedValues":[{"CountryCode":"-1","LanguageCode":"-1","Value":"GWo"}],"ReferenceId":0}},{"Id":14008714,"IsHome":false,"LocalizedNames":{"LocalizedValues":[{"CountryCode":"-1","LanguageCode":"-1","Value":"Webb Simpson"}],"ReferenceId":-1},"LocalizedShortNames":{"LocalizedValues":[{"CountryCode":"-1","LanguageCode":"-1","Value":"WSi"}],"ReferenceId":0}},{"Id":14008715,"IsHome":false,"LocalizedNames":{"LocalizedValues":[{"CountryCode":"-1","LanguageCode":"-1","Value":"Marc Leishman"}],"ReferenceId":-1},"LocalizedShortNames":{"LocalizedValues":[{"CountryCode":"-1","LanguageCode":"-1","Value":"MLe"}],"ReferenceId":0}},{"Id":14008716,"IsHome":false,"LocalizedNames":{"LocalizedValues":[{"CountryCode":"-1","LanguageCode":"-1","Value":"Shane Lowry"}],"ReferenceId":-1},"LocalizedShortNames":{"LocalizedValues":[{"CountryCode":"-1","LanguageCode":"-1","Value":"SLo"}],"ReferenceId":0}},{"Id":14008717,"IsHome":false,"LocalizedNames":{"LocalizedValues":[{"CountryCode":"-1","LanguageCode":"-1","Value":"Brandt Snedeker"}],"ReferenceId":-1},"LocalizedShortNames":{"LocalizedValues":[{"CountryCode":"-1","LanguageCode":"-1","Value":"BSn"}],"ReferenceId":0}},{"Id":14008718,"IsHome":false,"LocalizedNames":{"LocalizedValues":[{"CountryCode":"-1","LanguageCode":"-1","Value":"Bubba Watson"}],"ReferenceId":-1},"LocalizedShortNames":{"LocalizedValues":[{"CountryCode":"-1","LanguageCode":"-1","Value":"BWa"}],"ReferenceId":0}},{"Id":14008719,"IsHome":false,"LocalizedNames":{"LocalizedValues":[{"CountryCode":"-1","LanguageCode":"-1","Value":"Matt Wallace"}],"ReferenceId":-1},"LocalizedShortNames":{"LocalizedValues":[{"CountryCode":"-1","LanguageCode":"-1","Value":"MWa"}],"ReferenceId":0}},{"Id":14008720,"IsHome":false,"LocalizedNames":{"LocalizedValues":[{"CountryCode":"-1","LanguageCode":"-1","Value":"Cameron Smith"}],"ReferenceId":-1},"LocalizedShortNames":{"LocalizedValues":[{"CountryCode":"-1","LanguageCode":"-1","Value":"CSm"}],"ReferenceId":0}},{"Id":14008721,"IsHome":false,"LocalizedNames":{"LocalizedValues":[{"CountryCode":"-1","LanguageCode":"-1","Value":"Lucas Bjerregaard"}],"ReferenceId":-1},"LocalizedShortNames":{"LocalizedValues":[{"CountryCode":"-1","LanguageCode":"-1","Value":"LBj"}],"ReferenceId":0}},{"Id":14008722,"IsHome":false,"LocalizedNames":{"LocalizedValues":[{"CountryCode":"-1","LanguageCode":"-1","Value":"Rafa Cabrera Bello"}],"ReferenceId":-1},"LocalizedShortNames":{"LocalizedValues":[{"CountryCode":"-1","LanguageCode":"-1","Value":"RCa"}],"ReferenceId":0}},{"Id":14008723,"IsHome":false,"LocalizedNames":{"LocalizedValues":[{"CountryCode":"-1","LanguageCode":"-1","Value":"Danny Willett"}],"ReferenceId":-1},"LocalizedShortNames":{"LocalizedValues":[{"CountryCode":"-1","LanguageCode":"-1","Value":"DWi"}],"ReferenceId":0}},{"Id":14008724,"IsHome":false,"LocalizedNames":{"LocalizedValues":[{"CountryCode":"-1","LanguageCode":"-1","Value":"Matthew Fitzpatrick"}],"ReferenceId":-1},"LocalizedShortNames":{"LocalizedValues":[{"CountryCode":"-1","LanguageCode":"-1","Value":"MFi"}],"ReferenceId":0}},{"Id":14008725,"IsHome":false,"LocalizedNames":{"LocalizedValues":[{"CountryCode":"-1","LanguageCode":"-1","Value":"Kevin Kisner"}],"ReferenceId":-1},"LocalizedShortNames":{"LocalizedValues":[{"CountryCode":"-1","LanguageCode":"-1","Value":"KKi"}],"ReferenceId":0}},{"Id":14008726,"IsHome":false,"LocalizedNames":{"LocalizedValues":[{"CountryCode":"-1","LanguageCode":"-1","Value":"Ian Poulter"}],"ReferenceId":-1},"LocalizedShortNames":{"LocalizedValues":[{"CountryCode":"-1","LanguageCode":"-1","Value":"IPo"}],"ReferenceId":0}},{"Id":14008727,"IsHome":false,"LocalizedNames":{"LocalizedValues":[{"CountryCode":"-1","LanguageCode":"-1","Value":"Alex Noren"}],"ReferenceId":-1},"LocalizedShortNames":{"LocalizedValues":[{"CountryCode":"-1","LanguageCode":"-1","Value":"ANo"}],"ReferenceId":0}},{"Id":14008728,"IsHome":false,"LocalizedNames":{"LocalizedValues":[{"CountryCode":"-1","LanguageCode":"-1","Value":"Matthew Wolff"}],"ReferenceId":-1},"LocalizedShortNames":{"LocalizedValues":[{"CountryCode":"-1","LanguageCode":"-1","Value":"MWo"}],"ReferenceId":0}},{"Id":14008729,"IsHome":false,"LocalizedNames":{"LocalizedValues":[{"CountryCode":"-1","LanguageCode":"-1","Value":"Branden Grace"}],"ReferenceId":-1},"LocalizedShortNames":{"LocalizedValues":[{"CountryCode":"-1","LanguageCode":"-1","Value":"BGr"}],"ReferenceId":0}},{"Id":14008730,"IsHome":false,"LocalizedNames":{"LocalizedValues":[{"CountryCode":"-1","LanguageCode":"-1","Value":"Haotong Li"}],"ReferenceId":-1},"LocalizedShortNames":{"LocalizedValues":[{"CountryCode":"-1","LanguageCode":"-1","Value":"HLi"}],"ReferenceId":0}},{"Id":14008731,"IsHome":false,"LocalizedNames":{"LocalizedValues":[{"CountryCode":"-1","LanguageCode":"-1","Value":"Billy Horschel"}],"ReferenceId":-1},"LocalizedShortNames":{"LocalizedValues":[{"CountryCode":"-1","LanguageCode":"-1","Value":"BHo"}],"ReferenceId":0}},{"Id":14008732,"IsHome":false,"LocalizedNames":{"LocalizedValues":[{"CountryCode":"-1","LanguageCode":"-1","Value":"Keegan Bradley"}],"ReferenceId":-1},"LocalizedShortNames":{"LocalizedValues":[{"CountryCode":"-1","LanguageCode":"-1","Value":"KBr"}],"ReferenceId":0}},{"Id":14008733,"IsHome":false,"LocalizedNames":{"LocalizedValues":[{"CountryCode":"-1","LanguageCode":"-1","Value":"J.B. Holmes"}],"ReferenceId":-1},"LocalizedShortNames":{"LocalizedValues":[{"CountryCode":"-1","LanguageCode":"-1","Value":"JB"}],"ReferenceId":0}},{"Id":14008734,"IsHome":false,"LocalizedNames":{"LocalizedValues":[{"CountryCode":"-1","LanguageCode":"-1","Value":"Eddie Pepperell"}],"ReferenceId":-1},"LocalizedShortNames":{"LocalizedValues":[{"CountryCode":"-1","LanguageCode":"-1","Value":"EPe"}],"ReferenceId":0}},{"Id":14008735,"IsHome":false,"LocalizedNames":{"LocalizedValues":[{"CountryCode":"-1","LanguageCode":"-1","Value":"Thorbjorn Olesen"}],"ReferenceId":-1},"LocalizedShortNames":{"LocalizedValues":[{"CountryCode":"-1","LanguageCode":"-1","Value":"TOl"}],"ReferenceId":0}}],"IsActive":true,"SmartMarketReferenceGameTypeIds":"","ParentUniqueId":"16d74246-0ae1-4669-b9f0-7e88d9b7df4e","Parent2UniqueId":null,"Parent3UniqueId":null,"LastUpdated":"2020-06-25T08:00:17.8089303+02:00","NodeName":"Open de EE.UU. 2020","NodeId":"2550965664","Type":10,"SportHandle":"golf","Priority":0,"CountryCode":"","ParentNodeId":"634945983","ParentNodeName":"Open de EE.UU.","ParentNodePriority":0,"DisplayTypeName":"","Parent2NodeId":"488485541","Parent2NodeName":"EE.UU.","Parent2NodePriority":0,"Parent3NodeId":"377374333","Parent3NodeName":"Golf","Parent3NodePriority":100,"Parent4NodeId":"-1","Parent4NodeName":null,"Parent4NodePriority":0,"Parent5NodeId":"-1","Parent5NodeName":null,"Parent5NodePriority":0,"Parent6NodeId":"-1","Parent6NodeName":null,"Parent6NodePriority":0,"EventNodeTypeId":10,"TypeFilterList":null}},{"Key":"2550967323","Value":{"SpecialOddsValue":"","CategoryInfo":null,"CategoryInfos":[{"CategoryId":"90","CategoryName":"ANTEPOST BETTING","IsRelevant":true}],"LocalizedCategoryInfos":{"en":[{"CategoryId":"90","CategoryName":"ANTEPOST BETTING","IsRelevant":true}],"-1":[{"CategoryId":"90","CategoryName":"APUESTAS ANTICIPADAS","IsRelevant":true}]},"StartDate":"2020-09-17T11:00:00Z","GameTypeId":303,"SmartMarketAvailable":false,"ParentUniqueId":null,"Parent2UniqueId":"16d74246-0ae1-4669-b9f0-7e88d9b7df4e","Parent3UniqueId":null,"IsLive":false,"LastUpdated":"2020-06-25T08:00:17.8089303+02:00","NodeName":"Ganador","NodeId":"2550967323","Type":11,"IsActive":true,"SportHandle":"golf","Priority":0,"CountryCode":"","ParentNodeId":"2550965664","ParentNodeName":"Open de EE.UU. 2020","ParentNodePriority":0,"DisplayTypeName":"outrightlist","Parent2NodeId":"634945983","Parent2NodeName":"Open de EE.UU.","Parent2NodePriority":0,"Parent3NodeId":"488485541","Parent3NodeName":"EE.UU.","Parent3NodePriority":0,"Parent4NodeId":"377374333","Parent4NodeName":"Golf","Parent4NodePriority":100,"Parent5NodeId":"-1","Parent5NodeName":null,"Parent5NodePriority":0,"Parent6NodeId":"-1","Parent6NodeName":null,"Parent6NodePriority":0,"EventNodeTypeId":11,"TypeFilterList":null}},{"Key":"2550967360","Value":{"Odd":9.0,"SortOrder":0,"Tax":"Tax1|0,00|S;Tax2|0,00|S","GameTypeResultsNr":-1,"ParentUniqueId":null,"Parent2UniqueId":null,"Parent3UniqueId":"16d74246-0ae1-4669-b9f0-7e88d9b7df4e","IsLive":false,"LastUpdated":"2020-06-25T08:00:20.5120701+02:00","NodeName":"Brooks Koepka","NodeId":"2550967360","Type":12,"IsActive":true,"SportHandle":"golf","Priority":0,"CountryCode":"","ParentNodeId":"2550967323","ParentNodeName":"Ganador","ParentNodePriority":0,"DisplayTypeName":"","Parent2NodeId":"2550965664","Parent2NodeName":"Open de EE.UU. 2020","Parent2NodePriority":0,"Parent3NodeId":"634945983","Parent3NodeName":"Open de EE.UU.","Parent3NodePriority":0,"Parent4NodeId":"488485541","Parent4NodeName":"EE.UU.","Parent4NodePriority":0,"Parent5NodeId":"377374333","Parent5NodeName":"Golf","Parent5NodePriority":100,"Parent6NodeId":"-1","Parent6NodeName":null,"Parent6NodePriority":0,"EventNodeTypeId":12,"TypeFilterList":null}},{"Key":"2550967361","Value":{"Odd":9.0,"SortOrder":0,"Tax":"Tax1|0,00|S;Tax2|0,00|S","GameTypeResultsNr":-1,"ParentUniqueId":null,"Parent2UniqueId":null,"Parent3UniqueId":"16d74246-0ae1-4669-b9f0-7e88d9b7df4e","IsLive":false,"LastUpdated":"2020-06-25T08:00:20.5120701+02:00","NodeName":"Rory McIlroy","NodeId":"2550967361","Type":12,"IsActive":true,"SportHandle":"golf","Priority":0,"CountryCode":"","ParentNodeId":"2550967323","ParentNodeName":"Ganador","ParentNodePriority":0,"DisplayTypeName":"","Parent2NodeId":"2550965664","Parent2NodeName":"Open de EE.UU. 2020","Parent2NodePriority":0,"Parent3NodeId":"634945983","Parent3NodeName":"Open de EE.UU.","Parent3NodePriority":0,"Parent4NodeId":"488485541","Parent4NodeName":"EE.UU.","Parent4NodePriority":0,"Parent5NodeId":"377374333","Parent5NodeName":"Golf","Parent5NodePriority":100,"Parent6NodeId":"-1","Parent6NodeName":null,"Parent6NodePriority":0,"EventNodeTypeId":12,"TypeFilterList":null}},{"Key":"2550967362","Value":{"Odd":10.0,"SortOrder":0,"Tax":"Tax1|0,00|S;Tax2|0,00|S","GameTypeResultsNr":-1,"ParentUniqueId":null,"Parent2UniqueId":null,"Parent3UniqueId":"16d74246-0ae1-4669-b9f0-7e88d9b7df4e","IsLive":false,"LastUpdated":"2020-06-25T08:00:20.5120701+02:00","NodeName":"Dustin Johnson","NodeId":"2550967362","Type":12,"IsActive":true,"SportHandle":"golf","Priority":0,"CountryCode":"","ParentNodeId":"2550967323","ParentNodeName":"Ganador","ParentNodePriority":0,"DisplayTypeName":"","Parent2NodeId":"2550965664","Parent2NodeName":"Open de EE.UU. 2020","Parent2NodePriority":0,"Parent3NodeId":"634945983","Parent3NodeName":"Open de EE.UU.","Parent3NodePriority":0,"Parent4NodeId":"488485541","Parent4NodeName":"EE.UU.","Parent4NodePriority":0,"Parent5NodeId":"377374333","Parent5NodeName":"Golf","Parent5NodePriority":100,"Parent6NodeId":"-1","Parent6NodeName":null,"Parent6NodePriority":0,"EventNodeTypeId":12,"TypeFilterList":null}},{"Key":"2550967363","Value":{"Odd":12.0,"SortOrder":0,"Tax":"Tax1|0,00|S;Tax2|0,00|S","GameTypeResultsNr":-1,"ParentUniqueId":null,"Parent2UniqueId":null,"Parent3UniqueId":"16d74246-0ae1-4669-b9f0-7e88d9b7df4e","IsLive":false,"LastUpdated":"2020-06-25T08:00:20.5120701+02:00","NodeName":"Tiger Woods","NodeId":"2550967363","Type":12,"IsActive":true,"SportHandle":"golf","Priority":0,"CountryCode":"","ParentNodeId":"2550967323","ParentNodeName":"Ganador","ParentNodePriority":0,"DisplayTypeName":"","Parent2NodeId":"2550965664","Parent2NodeName":"Open de EE.UU. 2020","Parent2NodePriority":0,"Parent3NodeId":"634945983","Parent3NodeName":"Open de EE.UU.","Parent3NodePriority":0,"Parent4NodeId":"488485541","Parent4NodeName":"EE.UU.","Parent4NodePriority":0,"Parent5NodeId":"377374333","Parent5NodeName":"Golf","Parent5NodePriority":100,"Parent6NodeId":"-1","Parent6NodeName":null,"Parent6NodePriority":0,"EventNodeTypeId":12,"TypeFilterList":null}},{"Key":"2550967364","Value":{"Odd":15.0,"SortOrder":0,"Tax":"Tax1|0,00|S;Tax2|0,00|S","GameTypeResultsNr":-1,"ParentUniqueId":null,"Parent2UniqueId":null,"Parent3UniqueId":"16d74246-0ae1-4669-b9f0-7e88d9b7df4e","IsLive":false,"LastUpdated":"2020-06-25T08:00:20.5120701+02:00","NodeName":"Jon Rahm","NodeId":"2550967364","Type":12,"IsActive":true,"SportHandle":"golf","Priority":0,"CountryCode":"","ParentNodeId":"2550967323","ParentNodeName":"Ganador","ParentNodePriority":0,"DisplayTypeName":"","Parent2NodeId":"2550965664","Parent2NodeName":"Open de EE.UU. 2020","Parent2NodePriority":0,"Parent3NodeId":"634945983","Parent3NodeName":"Open de EE.UU.","Parent3NodePriority":0,"Parent4NodeId":"488485541","Parent4NodeName":"EE.UU.","Parent4NodePriority":0,"Parent5NodeId":"377374333","Parent5NodeName":"Golf","Parent5NodePriority":100,"Parent6NodeId":"-1","Parent6NodeName":null,"Parent6NodePriority":0,"EventNodeTypeId":12,"TypeFilterList":null}},{"Key":"2550967365","Value":{"Odd":20.0,"SortOrder":0,"Tax":"Tax1|0,00|S;Tax2|0,00|S","GameTypeResultsNr":-1,"ParentUniqueId":null,"Parent2UniqueId":null,"Parent3UniqueId":"16d74246-0ae1-4669-b9f0-7e88d9b7df4e","IsLive":false,"LastUpdated":"2020-06-25T08:00:20.5120701+02:00","NodeName":"Justin Rose","NodeId":"2550967365","Type":12,"IsActive":true,"SportHandle":"golf","Priority":0,"CountryCode":"","ParentNodeId":"2550967323","ParentNodeName":"Ganador","ParentNodePriority":0,"DisplayTypeName":"","Parent2NodeId":"2550965664","Parent2NodeName":"Open de EE.UU. 2020","Parent2NodePriority":0,"Parent3NodeId":"634945983","Parent3NodeName":"Open de EE.UU.","Parent3NodePriority":0,"Parent4NodeId":"488485541","Parent4NodeName":"EE.UU.","Parent4NodePriority":0,"Parent5NodeId":"377374333","Parent5NodeName":"Golf","Parent5NodePriority":100,"Parent6NodeId":"-1","Parent6NodeName":null,"Parent6NodePriority":0,"EventNodeTypeId":12,"TypeFilterList":null}},{"Key":"2550967366","Value":{"Odd":20.0,"SortOrder":0,"Tax":"Tax1|0,00|S;Tax2|0,00|S","GameTypeResultsNr":-1,"ParentUniqueId":null,"Parent2UniqueId":null,"Parent3UniqueId":"16d74246-0ae1-4669-b9f0-7e88d9b7df4e","IsLive":false,"LastUpdated":"2020-06-25T08:00:20.5120701+02:00","NodeName":"Jordan Spieth","NodeId":"2550967366","Type":12,"IsActive":true,"SportHandle":"golf","Priority":0,"CountryCode":"","ParentNodeId":"2550967323","ParentNodeName":"Ganador","ParentNodePriority":0,"DisplayTypeName":"","Parent2NodeId":"2550965664","Parent2NodeName":"Open de EE.UU. 2020","Parent2NodePriority":0,"Parent3NodeId":"634945983","Parent3NodeName":"Open de EE.UU.","Parent3NodePriority":0,"Parent4NodeId":"488485541","Parent4NodeName":"EE.UU.","Parent4NodePriority":0,"Parent5NodeId":"377374333","Parent5NodeName":"Golf","Parent5NodePriority":100,"Parent6NodeId":"-1","Parent6NodeName":null,"Parent6NodePriority":0,"EventNodeTypeId":12,"TypeFilterList":null}},{"Key":"2550967367","Value":{"Odd":20.0,"SortOrder":0,"Tax":"Tax1|0,00|S;Tax2|0,00|S","GameTypeResultsNr":-1,"ParentUniqueId":null,"Parent2UniqueId":null,"Parent3UniqueId":"16d74246-0ae1-4669-b9f0-7e88d9b7df4e","IsLive":false,"LastUpdated":"2020-06-25T08:00:20.5120701+02:00","NodeName":"Justin Thomas","NodeId":"2550967367","Type":12,"IsActive":true,"SportHandle":"golf","Priority":0,"CountryCode":"","ParentNodeId":"2550967323","ParentNodeName":"Ganador","ParentNodePriority":0,"DisplayTypeName":"","Parent2NodeId":"2550965664","Parent2NodeName":"Open de EE.UU. 2020","Parent2NodePriority":0,"Parent3NodeId":"634945983","Parent3NodeName":"Open de EE.UU.","Parent3NodePriority":0,"Parent4NodeId":"488485541","Parent4NodeName":"EE.UU.","Parent4NodePriority":0,"Parent5NodeId":"377374333","Parent5NodeName":"Golf","Parent5NodePriority":100,"Parent6NodeId":"-1","Parent6NodeName":null,"Parent6NodePriority":0,"EventNodeTypeId":12,"TypeFilterList":null}},{"Key":"2550967368","Value":{"Odd":20.0,"SortOrder":0,"Tax":"Tax1|0,00|S;Tax2|0,00|S","GameTypeResultsNr":-1,"ParentUniqueId":null,"Parent2UniqueId":null,"Parent3UniqueId":"16d74246-0ae1-4669-b9f0-7e88d9b7df4e","IsLive":false,"LastUpdated":"2020-06-25T08:00:20.5120701+02:00","NodeName":"Rickie Fowler","NodeId":"2550967368","Type":12,"IsActive":true,"SportHandle":"golf","Priority":0,"CountryCode":"","ParentNodeId":"2550967323","ParentNodeName":"Ganador","ParentNodePriority":0,"DisplayTypeName":"","Parent2NodeId":"2550965664","Parent2NodeName":"Open de EE.UU. 2020","Parent2NodePriority":0,"Parent3NodeId":"634945983","Parent3NodeName":"Open de EE.UU.","Parent3NodePriority":0,"Parent4NodeId":"488485541","Parent4NodeName":"EE.UU.","Parent4NodePriority":0,"Parent5NodeId":"377374333","Parent5NodeName":"Golf","Parent5NodePriority":100,"Parent6NodeId":"-1","Parent6NodeName":null,"Parent6NodePriority":0,"EventNodeTypeId":12,"TypeFilterList":null}},{"Key":"2550967369","Value":{"Odd":20.0,"SortOrder":0,"Tax":"Tax1|0,00|S;Tax2|0,00|S","GameTypeResultsNr":-1,"ParentUniqueId":null,"Parent2UniqueId":null,"Parent3UniqueId":"16d74246-0ae1-4669-b9f0-7e88d9b7df4e","IsLive":false,"LastUpdated":"2020-06-25T08:00:20.5120701+02:00","NodeName":"Xander Schauffele","NodeId":"2550967369","Type":12,"IsActive":true,"SportHandle":"golf","Priority":0,"CountryCode":"","ParentNodeId":"2550967323","ParentNodeName":"Ganador","ParentNodePriority":0,"DisplayTypeName":"","Parent2NodeId":"2550965664","Parent2NodeName":"Open de EE.UU. 2020","Parent2NodePriority":0,"Parent3NodeId":"634945983","Parent3NodeName":"Open de EE.UU.","Parent3NodePriority":0,"Parent4NodeId":"488485541","Parent4NodeName":"EE.UU.","Parent4NodePriority":0,"Parent5NodeId":"377374333","Parent5NodeName":"Golf","Parent5NodePriority":100,"Parent6NodeId":"-1","Parent6NodeName":null,"Parent6NodePriority":0,"EventNodeTypeId":12,"TypeFilterList":null}},{"Key":"2550967370","Value":{"Odd":20.0,"SortOrder":0,"Tax":"Tax1|0,00|S;Tax2|0,00|S","GameTypeResultsNr":-1,"ParentUniqueId":null,"Parent2UniqueId":null,"Parent3UniqueId":"16d74246-0ae1-4669-b9f0-7e88d9b7df4e","IsLive":false,"LastUpdated":"2020-06-25T08:00:20.5120701+02:00","NodeName":"Patrick Cantlay","NodeId":"2550967370","Type":12,"IsActive":true,"SportHandle":"golf","Priority":0,"CountryCode":"","ParentNodeId":"2550967323","ParentNodeName":"Ganador","ParentNodePriority":0,"DisplayTypeName":"","Parent2NodeId":"2550965664","Parent2NodeName":"Open de EE.UU. 2020","Parent2NodePriority":0,"Parent3NodeId":"634945983","Parent3NodeName":"Open de EE.UU.","Parent3NodePriority":0,"Parent4NodeId":"488485541","Parent4NodeName":"EE.UU.","Parent4NodePriority":0,"Parent5NodeId":"377374333","Parent5NodeName":"Golf","Parent5NodePriority":100,"Parent6NodeId":"-1","Parent6NodeName":null,"Parent6NodePriority":0,"EventNodeTypeId":12,"TypeFilterList":null}},{"Key":"2550967371","Value":{"Odd":30.0,"SortOrder":0,"Tax":"Tax1|0,00|S;Tax2|0,00|S","GameTypeResultsNr":-1,"ParentUniqueId":null,"Parent2UniqueId":null,"Parent3UniqueId":"16d74246-0ae1-4669-b9f0-7e88d9b7df4e","IsLive":false,"LastUpdated":"2020-06-25T08:00:20.5120701+02:00","NodeName":"Jason Day","NodeId":"2550967371","Type":12,"IsActive":true,"SportHandle":"golf","Priority":0,"CountryCode":"","ParentNodeId":"2550967323","ParentNodeName":"Ganador","ParentNodePriority":0,"DisplayTypeName":"","Parent2NodeId":"2550965664","Parent2NodeName":"Open de EE.UU. 2020","Parent2NodePriority":0,"Parent3NodeId":"634945983","Parent3NodeName":"Open de EE.UU.","Parent3NodePriority":0,"Parent4NodeId":"488485541","Parent4NodeName":"EE.UU.","Parent4NodePriority":0,"Parent5NodeId":"377374333","Parent5NodeName":"Golf","Parent5NodePriority":100,"Parent6NodeId":"-1","Parent6NodeName":null,"Parent6NodePriority":0,"EventNodeTypeId":12,"TypeFilterList":null}},{"Key":"2550967372","Value":{"Odd":40.0,"SortOrder":0,"Tax":"Tax1|0,00|S;Tax2|0,00|S","GameTypeResultsNr":-1,"ParentUniqueId":null,"Parent2UniqueId":null,"Parent3UniqueId":"16d74246-0ae1-4669-b9f0-7e88d9b7df4e","IsLive":false,"LastUpdated":"2020-06-25T08:00:20.5120701+02:00","NodeName":"Francesco Molinari","NodeId":"2550967372","Type":12,"IsActive":true,"SportHandle":"golf","Priority":0,"CountryCode":"","ParentNodeId":"2550967323","ParentNodeName":"Ganador","ParentNodePriority":0,"DisplayTypeName":"","Parent2NodeId":"2550965664","Parent2NodeName":"Open de EE.UU. 2020","Parent2NodePriority":0,"Parent3NodeId":"634945983","Parent3NodeName":"Open de EE.UU.","Parent3NodePriority":0,"Parent4NodeId":"488485541","Parent4NodeName":"EE.UU.","Parent4NodePriority":0,"Parent5NodeId":"377374333","Parent5NodeName":"Golf","Parent5NodePriority":100,"Parent6NodeId":"-1","Parent6NodeName":null,"Parent6NodePriority":0,"EventNodeTypeId":12,"TypeFilterList":null}},{"Key":"2550967373","Value":{"Odd":30.0,"SortOrder":0,"Tax":"Tax1|0,00|S;Tax2|0,00|S","GameTypeResultsNr":-1,"ParentUniqueId":null,"Parent2UniqueId":null,"Parent3UniqueId":"16d74246-0ae1-4669-b9f0-7e88d9b7df4e","IsLive":false,"LastUpdated":"2020-06-25T08:00:20.5120701+02:00","NodeName":"Tommy Fleetwood","NodeId":"2550967373","Type":12,"IsActive":true,"SportHandle":"golf","Priority":0,"CountryCode":"","ParentNodeId":"2550967323","ParentNodeName":"Ganador","ParentNodePriority":0,"DisplayTypeName":"","Parent2NodeId":"2550965664","Parent2NodeName":"Open de EE.UU. 2020","Parent2NodePriority":0,"Parent3NodeId":"634945983","Parent3NodeName":"Open de EE.UU.","Parent3NodePriority":0,"Parent4NodeId":"488485541","Parent4NodeName":"EE.UU.","Parent4NodePriority":0,"Parent5NodeId":"377374333","Parent5NodeName":"Golf","Parent5NodePriority":100,"Parent6NodeId":"-1","Parent6NodeName":null,"Parent6NodePriority":0,"EventNodeTypeId":12,"TypeFilterList":null}},{"Key":"2550967374","Value":{"Odd":30.0,"SortOrder":0,"Tax":"Tax1|0,00|S;Tax2|0,00|S","GameTypeResultsNr":-1,"ParentUniqueId":null,"Parent2UniqueId":null,"Parent3UniqueId":"16d74246-0ae1-4669-b9f0-7e88d9b7df4e","IsLive":false,"LastUpdated":"2020-06-25T08:00:20.5120701+02:00","NodeName":"Hideki Matsuyama","NodeId":"2550967374","Type":12,"IsActive":true,"SportHandle":"golf","Priority":0,"CountryCode":"","ParentNodeId":"2550967323","ParentNodeName":"Ganador","ParentNodePriority":0,"DisplayTypeName":"","Parent2NodeId":"2550965664","Parent2NodeName":"Open de EE.UU. 2020","Parent2NodePriority":0,"Parent3NodeId":"634945983","Parent3NodeName":"Open de EE.UU.","Parent3NodePriority":0,"Parent4NodeId":"488485541","Parent4NodeName":"EE.UU.","Parent4NodePriority":0,"Parent5NodeId":"377374333","Parent5NodeName":"Golf","Parent5NodePriority":100,"Parent6NodeId":"-1","Parent6NodeName":null,"Parent6NodePriority":0,"EventNodeTypeId":12,"TypeFilterList":null}},{"Key":"2550967375","Value":{"Odd":30.0,"SortOrder":0,"Tax":"Tax1|0,00|S;Tax2|0,00|S","GameTypeResultsNr":-1,"ParentUniqueId":null,"Parent2UniqueId":null,"Parent3UniqueId":"16d74246-0ae1-4669-b9f0-7e88d9b7df4e","IsLive":false,"LastUpdated":"2020-06-25T08:00:20.5120701+02:00","NodeName":"Bryson DeChambeau","NodeId":"2550967375","Type":12,"IsActive":true,"SportHandle":"golf","Priority":0,"CountryCode":"","ParentNodeId":"2550967323","ParentNodeName":"Ganador","ParentNodePriority":0,"DisplayTypeName":"","Parent2NodeId":"2550965664","Parent2NodeName":"Open de EE.UU. 2020","Parent2NodePriority":0,"Parent3NodeId":"634945983","Parent3NodeName":"Open de EE.UU.","Parent3NodePriority":0,"Parent4NodeId":"488485541","Parent4NodeName":"EE.UU.","Parent4NodePriority":0,"Parent5NodeId":"377374333","Parent5NodeName":"Golf","Parent5NodePriority":100,"Parent6NodeId":"-1","Parent6NodeName":null,"Parent6NodePriority":0,"EventNodeTypeId":12,"TypeFilterList":null}},{"Key":"2550967376","Value":{"Odd":30.0,"SortOrder":0,"Tax":"Tax1|0,00|S;Tax2|0,00|S","GameTypeResultsNr":-1,"ParentUniqueId":null,"Parent2UniqueId":null,"Parent3UniqueId":"16d74246-0ae1-4669-b9f0-7e88d9b7df4e","IsLive":false,"LastUpdated":"2020-06-25T08:00:20.5120701+02:00","NodeName":"Adam Scott","NodeId":"2550967376","Type":12,"IsActive":true,"SportHandle":"golf","Priority":0,"CountryCode":"","ParentNodeId":"2550967323","ParentNodeName":"Ganador","ParentNodePriority":0,"DisplayTypeName":"","Parent2NodeId":"2550965664","Parent2NodeName":"Open de EE.UU. 2020","Parent2NodePriority":0,"Parent3NodeId":"634945983","Parent3NodeName":"Open de EE.UU.","Parent3NodePriority":0,"Parent4NodeId":"488485541","Parent4NodeName":"EE.UU.","Parent4NodePriority":0,"Parent5NodeId":"377374333","Parent5NodeName":"Golf","Parent5NodePriority":100,"Parent6NodeId":"-1","Parent6NodeName":null,"Parent6NodePriority":0,"EventNodeTypeId":12,"TypeFilterList":null}},{"Key":"2550967377","Value":{"Odd":40.0,"SortOrder":0,"Tax":"Tax1|0,00|S;Tax2|0,00|S","GameTypeResultsNr":-1,"ParentUniqueId":null,"Parent2UniqueId":null,"Parent3UniqueId":"16d74246-0ae1-4669-b9f0-7e88d9b7df4e","IsLive":false,"LastUpdated":"2020-06-25T08:00:20.5120701+02:00","NodeName":"Tony Finau","NodeId":"2550967377","Type":12,"IsActive":true,"SportHandle":"golf","Priority":0,"CountryCode":"","ParentNodeId":"2550967323","ParentNodeName":"Ganador","ParentNodePriority":0,"DisplayTypeName":"","Parent2NodeId":"2550965664","Parent2NodeName":"Open de EE.UU. 2020","Parent2NodePriority":0,"Parent3NodeId":"634945983","Parent3NodeName":"Open de EE.UU.","Parent3NodePriority":0,"Parent4NodeId":"488485541","Parent4NodeName":"EE.UU.","Parent4NodePriority":0,"Parent5NodeId":"377374333","Parent5NodeName":"Golf","Parent5NodePriority":100,"Parent6NodeId":"-1","Parent6NodeName":null,"Parent6NodePriority":0,"EventNodeTypeId":12,"TypeFilterList":null}},{"Key":"2550967378","Value":{"Odd":40.0,"SortOrder":0,"Tax":"Tax1|0,00|S;Tax2|0,00|S","GameTypeResultsNr":-1,"ParentUniqueId":null,"Parent2UniqueId":null,"Parent3UniqueId":"16d74246-0ae1-4669-b9f0-7e88d9b7df4e","IsLive":false,"LastUpdated":"2020-06-25T08:00:20.5120701+02:00","NodeName":"Paul Casey","NodeId":"2550967378","Type":12,"IsActive":true,"SportHandle":"golf","Priority":0,"CountryCode":"","ParentNodeId":"2550967323","ParentNodeName":"Ganador","ParentNodePriority":0,"DisplayTypeName":"","Parent2NodeId":"2550965664","Parent2NodeName":"Open de EE.UU. 2020","Parent2NodePriority":0,"Parent3NodeId":"634945983","Parent3NodeName":"Open de EE.UU.","Parent3NodePriority":0,"Parent4NodeId":"488485541","Parent4NodeName":"EE.UU.","Parent4NodePriority":0,"Parent5NodeId":"377374333","Parent5NodeName":"Golf","Parent5NodePriority":100,"Parent6NodeId":"-1","Parent6NodeName":null,"Parent6NodePriority":0,"EventNodeTypeId":12,"TypeFilterList":null}},{"Key":"2550967379","Value":{"Odd":40.0,"SortOrder":0,"Tax":"Tax1|0,00|S;Tax2|0,00|S","GameTypeResultsNr":-1,"ParentUniqueId":null,"Parent2UniqueId":null,"Parent3UniqueId":"16d74246-0ae1-4669-b9f0-7e88d9b7df4e","IsLive":false,"LastUpdated":"2020-06-25T08:00:20.5120701+02:00","NodeName":"Patrick Reed","NodeId":"2550967379","Type":12,"IsActive":true,"SportHandle":"golf","Priority":0,"CountryCode":"","ParentNodeId":"2550967323","ParentNodeName":"Ganador","ParentNodePriority":0,"DisplayTypeName":"","Parent2NodeId":"2550965664","Parent2NodeName":"Open de EE.UU. 2020","Parent2NodePriority":0,"Parent3NodeId":"634945983","Parent3NodeName":"Open de EE.UU.","Parent3NodePriority":0,"Parent4NodeId":"488485541","Parent4NodeName":"EE.UU.","Parent4NodePriority":0,"Parent5NodeId":"377374333","Parent5NodeName":"Golf","Parent5NodePriority":100,"Parent6NodeId":"-1","Parent6NodeName":null,"Parent6NodePriority":0,"EventNodeTypeId":12,"TypeFilterList":null}},{"Key":"2550967380","Value":{"Odd":65.0,"SortOrder":0,"Tax":"Tax1|0,00|S;Tax2|0,00|S","GameTypeResultsNr":-1,"ParentUniqueId":null,"Parent2UniqueId":null,"Parent3UniqueId":"16d74246-0ae1-4669-b9f0-7e88d9b7df4e","IsLive":false,"LastUpdated":"2020-06-25T08:00:20.5120701+02:00","NodeName":"Henrik Stenson","NodeId":"2550967380","Type":12,"IsActive":true,"SportHandle":"golf","Priority":0,"CountryCode":"","ParentNodeId":"2550967323","ParentNodeName":"Ganador","ParentNodePriority":0,"DisplayTypeName":"","Parent2NodeId":"2550965664","Parent2NodeName":"Open de EE.UU. 2020","Parent2NodePriority":0,"Parent3NodeId":"634945983","Parent3NodeName":"Open de EE.UU.","Parent3NodePriority":0,"Parent4NodeId":"488485541","Parent4NodeName":"EE.UU.","Parent4NodePriority":0,"Parent5NodeId":"377374333","Parent5NodeName":"Golf","Parent5NodePriority":100,"Parent6NodeId":"-1","Parent6NodeName":null,"Parent6NodePriority":0,"EventNodeTypeId":12,"TypeFilterList":null}},{"Key":"2550967381","Value":{"Odd":50.0,"SortOrder":0,"Tax":"Tax1|0,00|S;Tax2|0,00|S","GameTypeResultsNr":-1,"ParentUniqueId":null,"Parent2UniqueId":null,"Parent3UniqueId":"16d74246-0ae1-4669-b9f0-7e88d9b7df4e","IsLive":false,"LastUpdated":"2020-06-25T08:00:20.5120701+02:00","NodeName":"Matt Kuchar","NodeId":"2550967381","Type":12,"IsActive":true,"SportHandle":"golf","Priority":0,"CountryCode":"","ParentNodeId":"2550967323","ParentNodeName":"Ganador","ParentNodePriority":0,"DisplayTypeName":"","Parent2NodeId":"2550965664","Parent2NodeName":"Open de EE.UU. 2020","Parent2NodePriority":0,"Parent3NodeId":"634945983","Parent3NodeName":"Open de EE.UU.","Parent3NodePriority":0,"Parent4NodeId":"488485541","Parent4NodeName":"EE.UU.","Parent4NodePriority":0,"Parent5NodeId":"377374333","Parent5NodeName":"Golf","Parent5NodePriority":100,"Parent6NodeId":"-1","Parent6NodeName":null,"Parent6NodePriority":0,"EventNodeTypeId":12,"TypeFilterList":null}},{"Key":"2550967382","Value":{"Odd":50.0,"SortOrder":0,"Tax":"Tax1|0,00|S;Tax2|0,00|S","GameTypeResultsNr":-1,"ParentUniqueId":null,"Parent2UniqueId":null,"Parent3UniqueId":"16d74246-0ae1-4669-b9f0-7e88d9b7df4e","IsLive":false,"LastUpdated":"2020-06-25T08:00:20.5120701+02:00","NodeName":"Sergio García","NodeId":"2550967382","Type":12,"IsActive":true,"SportHandle":"golf","Priority":0,"CountryCode":"","ParentNodeId":"2550967323","ParentNodeName":"Ganador","ParentNodePriority":0,"DisplayTypeName":"","Parent2NodeId":"2550965664","Parent2NodeName":"Open de EE.UU. 2020","Parent2NodePriority":0,"Parent3NodeId":"634945983","Parent3NodeName":"Open de EE.UU.","Parent3NodePriority":0,"Parent4NodeId":"488485541","Parent4NodeName":"EE.UU.","Parent4NodePriority":0,"Parent5NodeId":"377374333","Parent5NodeName":"Golf","Parent5NodePriority":100,"Parent6NodeId":"-1","Parent6NodeName":null,"Parent6NodePriority":0,"EventNodeTypeId":12,"TypeFilterList":null}},{"Key":"2550967383","Value":{"Odd":75.0,"SortOrder":0,"Tax":"Tax1|0,00|S;Tax2|0,00|S","GameTypeResultsNr":-1,"ParentUniqueId":null,"Parent2UniqueId":null,"Parent3UniqueId":"16d74246-0ae1-4669-b9f0-7e88d9b7df4e","IsLive":false,"LastUpdated":"2020-06-25T08:00:20.5120701+02:00","NodeName":"Phil Mickelson","NodeId":"2550967383","Type":12,"IsActive":true,"SportHandle":"golf","Priority":0,"CountryCode":"","ParentNodeId":"2550967323","ParentNodeName":"Ganador","ParentNodePriority":0,"DisplayTypeName":"","Parent2NodeId":"2550965664","Parent2NodeName":"Open de EE.UU. 2020","Parent2NodePriority":0,"Parent3NodeId":"634945983","Parent3NodeName":"Open de EE.UU.","Parent3NodePriority":0,"Parent4NodeId":"488485541","Parent4NodeName":"EE.UU.","Parent4NodePriority":0,"Parent5NodeId":"377374333","Parent5NodeName":"Golf","Parent5NodePriority":100,"Parent6NodeId":"-1","Parent6NodeName":null,"Parent6NodePriority":0,"EventNodeTypeId":12,"TypeFilterList":null}},{"Key":"2550967384","Value":{"Odd":50.0,"SortOrder":0,"Tax":"Tax1|0,00|S;Tax2|0,00|S","GameTypeResultsNr":-1,"ParentUniqueId":null,"Parent2UniqueId":null,"Parent3UniqueId":"16d74246-0ae1-4669-b9f0-7e88d9b7df4e","IsLive":false,"LastUpdated":"2020-06-25T08:00:20.5120701+02:00","NodeName":"Louis Oosthuizen","NodeId":"2550967384","Type":12,"IsActive":true,"SportHandle":"golf","Priority":0,"CountryCode":"","ParentNodeId":"2550967323","ParentNodeName":"Ganador","ParentNodePriority":0,"DisplayTypeName":"","Parent2NodeId":"2550965664","Parent2NodeName":"Open de EE.UU. 2020","Parent2NodePriority":0,"Parent3NodeId":"634945983","Parent3NodeName":"Open de EE.UU.","Parent3NodePriority":0,"Parent4NodeId":"488485541","Parent4NodeName":"EE.UU.","Parent4NodePriority":0,"Parent5NodeId":"377374333","Parent5NodeName":"Golf","Parent5NodePriority":100,"Parent6NodeId":"-1","Parent6NodeName":null,"Parent6NodePriority":0,"EventNodeTypeId":12,"TypeFilterList":null}},{"Key":"2550967385","Value":{"Odd":50.0,"SortOrder":0,"Tax":"Tax1|0,00|S;Tax2|0,00|S","GameTypeResultsNr":-1,"ParentUniqueId":null,"Parent2UniqueId":null,"Parent3UniqueId":"16d74246-0ae1-4669-b9f0-7e88d9b7df4e","IsLive":false,"LastUpdated":"2020-06-25T08:00:20.5120701+02:00","NodeName":"Gary Woodland","NodeId":"2550967385","Type":12,"IsActive":true,"SportHandle":"golf","Priority":0,"CountryCode":"","ParentNodeId":"2550967323","ParentNodeName":"Ganador","ParentNodePriority":0,"DisplayTypeName":"","Parent2NodeId":"2550965664","Parent2NodeName":"Open de EE.UU. 2020","Parent2NodePriority":0,"Parent3NodeId":"634945983","Parent3NodeName":"Open de EE.UU.","Parent3NodePriority":0,"Parent4NodeId":"488485541","Parent4NodeName":"EE.UU.","Parent4NodePriority":0,"Parent5NodeId":"377374333","Parent5NodeName":"Golf","Parent5NodePriority":100,"Parent6NodeId":"-1","Parent6NodeName":null,"Parent6NodePriority":0,"EventNodeTypeId":12,"TypeFilterList":null}},{"Key":"2550967386","Value":{"Odd":50.0,"SortOrder":0,"Tax":"Tax1|0,00|S;Tax2|0,00|S","GameTypeResultsNr":-1,"ParentUniqueId":null,"Parent2UniqueId":null,"Parent3UniqueId":"16d74246-0ae1-4669-b9f0-7e88d9b7df4e","IsLive":false,"LastUpdated":"2020-06-25T08:00:20.5120701+02:00","NodeName":"Webb Simpson","NodeId":"2550967386","Type":12,"IsActive":true,"SportHandle":"golf","Priority":0,"CountryCode":"","ParentNodeId":"2550967323","ParentNodeName":"Ganador","ParentNodePriority":0,"DisplayTypeName":"","Parent2NodeId":"2550965664","Parent2NodeName":"Open de EE.UU. 2020","Parent2NodePriority":0,"Parent3NodeId":"634945983","Parent3NodeName":"Open de EE.UU.","Parent3NodePriority":0,"Parent4NodeId":"488485541","Parent4NodeName":"EE.UU.","Parent4NodePriority":0,"Parent5NodeId":"377374333","Parent5NodeName":"Golf","Parent5NodePriority":100,"Parent6NodeId":"-1","Parent6NodeName":null,"Parent6NodePriority":0,"EventNodeTypeId":12,"TypeFilterList":null}},{"Key":"2550967387","Value":{"Odd":65.0,"SortOrder":0,"Tax":"Tax1|0,00|S;Tax2|0,00|S","GameTypeResultsNr":-1,"ParentUniqueId":null,"Parent2UniqueId":null,"Parent3UniqueId":"16d74246-0ae1-4669-b9f0-7e88d9b7df4e","IsLive":false,"LastUpdated":"2020-06-25T08:00:20.5120701+02:00","NodeName":"Marc Leishman","NodeId":"2550967387","Type":12,"IsActive":true,"SportHandle":"golf","Priority":0,"CountryCode":"","ParentNodeId":"2550967323","ParentNodeName":"Ganador","ParentNodePriority":0,"DisplayTypeName":"","Parent2NodeId":"2550965664","Parent2NodeName":"Open de EE.UU. 2020","Parent2NodePriority":0,"Parent3NodeId":"634945983","Parent3NodeName":"Open de EE.UU.","Parent3NodePriority":0,"Parent4NodeId":"488485541","Parent4NodeName":"EE.UU.","Parent4NodePriority":0,"Parent5NodeId":"377374333","Parent5NodeName":"Golf","Parent5NodePriority":100,"Parent6NodeId":"-1","Parent6NodeName":null,"Parent6NodePriority":0,"EventNodeTypeId":12,"TypeFilterList":null}},{"Key":"2550967388","Value":{"Odd":65.0,"SortOrder":0,"Tax":"Tax1|0,00|S;Tax2|0,00|S","GameTypeResultsNr":-1,"ParentUniqueId":null,"Parent2UniqueId":null,"Parent3UniqueId":"16d74246-0ae1-4669-b9f0-7e88d9b7df4e","IsLive":false,"LastUpdated":"2020-06-25T08:00:20.5120701+02:00","NodeName":"Shane Lowry","NodeId":"2550967388","Type":12,"IsActive":true,"SportHandle":"golf","Priority":0,"CountryCode":"","ParentNodeId":"2550967323","ParentNodeName":"Ganador","ParentNodePriority":0,"DisplayTypeName":"","Parent2NodeId":"2550965664","Parent2NodeName":"Open de EE.UU. 2020","Parent2NodePriority":0,"Parent3NodeId":"634945983","Parent3NodeName":"Open de EE.UU.","Parent3NodePriority":0,"Parent4NodeId":"488485541","Parent4NodeName":"EE.UU.","Parent4NodePriority":0,"Parent5NodeId":"377374333","Parent5NodeName":"Golf","Parent5NodePriority":100,"Parent6NodeId":"-1","Parent6NodeName":null,"Parent6NodePriority":0,"EventNodeTypeId":12,"TypeFilterList":null}},{"Key":"2550967389","Value":{"Odd":65.0,"SortOrder":0,"Tax":"Tax1|0,00|S;Tax2|0,00|S","GameTypeResultsNr":-1,"ParentUniqueId":null,"Parent2UniqueId":null,"Parent3UniqueId":"16d74246-0ae1-4669-b9f0-7e88d9b7df4e","IsLive":false,"LastUpdated":"2020-06-25T08:00:20.5120701+02:00","NodeName":"Brandt Snedeker","NodeId":"2550967389","Type":12,"IsActive":true,"SportHandle":"golf","Priority":0,"CountryCode":"","ParentNodeId":"2550967323","ParentNodeName":"Ganador","ParentNodePriority":0,"DisplayTypeName":"","Parent2NodeId":"2550965664","Parent2NodeName":"Open de EE.UU. 2020","Parent2NodePriority":0,"Parent3NodeId":"634945983","Parent3NodeName":"Open de EE.UU.","Parent3NodePriority":0,"Parent4NodeId":"488485541","Parent4NodeName":"EE.UU.","Parent4NodePriority":0,"Parent5NodeId":"377374333","Parent5NodeName":"Golf","Parent5NodePriority":100,"Parent6NodeId":"-1","Parent6NodeName":null,"Parent6NodePriority":0,"EventNodeTypeId":12,"TypeFilterList":null}},{"Key":"2550967390","Value":{"Odd":80.0,"SortOrder":0,"Tax":"Tax1|0,00|S;Tax2|0,00|S","GameTypeResultsNr":-1,"ParentUniqueId":null,"Parent2UniqueId":null,"Parent3UniqueId":"16d74246-0ae1-4669-b9f0-7e88d9b7df4e","IsLive":false,"LastUpdated":"2020-06-25T08:00:20.5120701+02:00","NodeName":"Bubba Watson","NodeId":"2550967390","Type":12,"IsActive":true,"SportHandle":"golf","Priority":0,"CountryCode":"","ParentNodeId":"2550967323","ParentNodeName":"Ganador","ParentNodePriority":0,"DisplayTypeName":"","Parent2NodeId":"2550965664","Parent2NodeName":"Open de EE.UU. 2020","Parent2NodePriority":0,"Parent3NodeId":"634945983","Parent3NodeName":"Open de EE.UU.","Parent3NodePriority":0,"Parent4NodeId":"488485541","Parent4NodeName":"EE.UU.","Parent4NodePriority":0,"Parent5NodeId":"377374333","Parent5NodeName":"Golf","Parent5NodePriority":100,"Parent6NodeId":"-1","Parent6NodeName":null,"Parent6NodePriority":0,"EventNodeTypeId":12,"TypeFilterList":null}},{"Key":"2550967391","Value":{"Odd":80.0,"SortOrder":0,"Tax":"Tax1|0,00|S;Tax2|0,00|S","GameTypeResultsNr":-1,"ParentUniqueId":null,"Parent2UniqueId":null,"Parent3UniqueId":"16d74246-0ae1-4669-b9f0-7e88d9b7df4e","IsLive":false,"LastUpdated":"2020-06-25T08:00:20.5120701+02:00","NodeName":"Matt Wallace","NodeId":"2550967391","Type":12,"IsActive":true,"SportHandle":"golf","Priority":0,"CountryCode":"","ParentNodeId":"2550967323","ParentNodeName":"Ganador","ParentNodePriority":0,"DisplayTypeName":"","Parent2NodeId":"2550965664","Parent2NodeName":"Open de EE.UU. 2020","Parent2NodePriority":0,"Parent3NodeId":"634945983","Parent3NodeName":"Open de EE.UU.","Parent3NodePriority":0,"Parent4NodeId":"488485541","Parent4NodeName":"EE.UU.","Parent4NodePriority":0,"Parent5NodeId":"377374333","Parent5NodeName":"Golf","Parent5NodePriority":100,"Parent6NodeId":"-1","Parent6NodeName":null,"Parent6NodePriority":0,"EventNodeTypeId":12,"TypeFilterList":null}},{"Key":"2550967392","Value":{"Odd":80.0,"SortOrder":0,"Tax":"Tax1|0,00|S;Tax2|0,00|S","GameTypeResultsNr":-1,"ParentUniqueId":null,"Parent2UniqueId":null,"Parent3UniqueId":"16d74246-0ae1-4669-b9f0-7e88d9b7df4e","IsLive":false,"LastUpdated":"2020-06-25T08:00:20.5120701+02:00","NodeName":"Cameron Smith","NodeId":"2550967392","Type":12,"IsActive":true,"SportHandle":"golf","Priority":0,"CountryCode":"","ParentNodeId":"2550967323","ParentNodeName":"Ganador","ParentNodePriority":0,"DisplayTypeName":"","Parent2NodeId":"2550965664","Parent2NodeName":"Open de EE.UU. 2020","Parent2NodePriority":0,"Parent3NodeId":"634945983","Parent3NodeName":"Open de EE.UU.","Parent3NodePriority":0,"Parent4NodeId":"488485541","Parent4NodeName":"EE.UU.","Parent4NodePriority":0,"Parent5NodeId":"377374333","Parent5NodeName":"Golf","Parent5NodePriority":100,"Parent6NodeId":"-1","Parent6NodeName":null,"Parent6NodePriority":0,"EventNodeTypeId":12,"TypeFilterList":null}},{"Key":"2550967393","Value":{"Odd":80.0,"SortOrder":0,"Tax":"Tax1|0,00|S;Tax2|0,00|S","GameTypeResultsNr":-1,"ParentUniqueId":null,"Parent2UniqueId":null,"Parent3UniqueId":"16d74246-0ae1-4669-b9f0-7e88d9b7df4e","IsLive":false,"LastUpdated":"2020-06-25T08:00:20.5120701+02:00","NodeName":"Lucas Bjerregaard","NodeId":"2550967393","Type":12,"IsActive":true,"SportHandle":"golf","Priority":0,"CountryCode":"","ParentNodeId":"2550967323","ParentNodeName":"Ganador","ParentNodePriority":0,"DisplayTypeName":"","Parent2NodeId":"2550965664","Parent2NodeName":"Open de EE.UU. 2020","Parent2NodePriority":0,"Parent3NodeId":"634945983","Parent3NodeName":"Open de EE.UU.","Parent3NodePriority":0,"Parent4NodeId":"488485541","Parent4NodeName":"EE.UU.","Parent4NodePriority":0,"Parent5NodeId":"377374333","Parent5NodeName":"Golf","Parent5NodePriority":100,"Parent6NodeId":"-1","Parent6NodeName":null,"Parent6NodePriority":0,"EventNodeTypeId":12,"TypeFilterList":null}},{"Key":"2550967394","Value":{"Odd":80.0,"SortOrder":0,"Tax":"Tax1|0,00|S;Tax2|0,00|S","GameTypeResultsNr":-1,"ParentUniqueId":null,"Parent2UniqueId":null,"Parent3UniqueId":"16d74246-0ae1-4669-b9f0-7e88d9b7df4e","IsLive":false,"LastUpdated":"2020-06-25T08:00:20.5120701+02:00","NodeName":"Rafa Cabrera Bello","NodeId":"2550967394","Type":12,"IsActive":true,"SportHandle":"golf","Priority":0,"CountryCode":"","ParentNodeId":"2550967323","ParentNodeName":"Ganador","ParentNodePriority":0,"DisplayTypeName":"","Parent2NodeId":"2550965664","Parent2NodeName":"Open de EE.UU. 2020","Parent2NodePriority":0,"Parent3NodeId":"634945983","Parent3NodeName":"Open de EE.UU.","Parent3NodePriority":0,"Parent4NodeId":"488485541","Parent4NodeName":"EE.UU.","Parent4NodePriority":0,"Parent5NodeId":"377374333","Parent5NodeName":"Golf","Parent5NodePriority":100,"Parent6NodeId":"-1","Parent6NodeName":null,"Parent6NodePriority":0,"EventNodeTypeId":12,"TypeFilterList":null}},{"Key":"2550967395","Value":{"Odd":100.0,"SortOrder":0,"Tax":"Tax1|0,00|S;Tax2|0,00|S","GameTypeResultsNr":-1,"ParentUniqueId":null,"Parent2UniqueId":null,"Parent3UniqueId":"16d74246-0ae1-4669-b9f0-7e88d9b7df4e","IsLive":false,"LastUpdated":"2020-06-25T08:00:20.5120701+02:00","NodeName":"Danny Willett","NodeId":"2550967395","Type":12,"IsActive":true,"SportHandle":"golf","Priority":0,"CountryCode":"","ParentNodeId":"2550967323","ParentNodeName":"Ganador","ParentNodePriority":0,"DisplayTypeName":"","Parent2NodeId":"2550965664","Parent2NodeName":"Open de EE.UU. 2020","Parent2NodePriority":0,"Parent3NodeId":"634945983","Parent3NodeName":"Open de EE.UU.","Parent3NodePriority":0,"Parent4NodeId":"488485541","Parent4NodeName":"EE.UU.","Parent4NodePriority":0,"Parent5NodeId":"377374333","Parent5NodeName":"Golf","Parent5NodePriority":100,"Parent6NodeId":"-1","Parent6NodeName":null,"Parent6NodePriority":0,"EventNodeTypeId":12,"TypeFilterList":null}},{"Key":"2550967396","Value":{"Odd":100.0,"SortOrder":0,"Tax":"Tax1|0,00|S;Tax2|0,00|S","GameTypeResultsNr":-1,"ParentUniqueId":null,"Parent2UniqueId":null,"Parent3UniqueId":"16d74246-0ae1-4669-b9f0-7e88d9b7df4e","IsLive":false,"LastUpdated":"2020-06-25T08:00:20.5120701+02:00","NodeName":"Matthew Fitzpatrick","NodeId":"2550967396","Type":12,"IsActive":true,"SportHandle":"golf","Priority":0,"CountryCode":"","ParentNodeId":"2550967323","ParentNodeName":"Ganador","ParentNodePriority":0,"DisplayTypeName":"","Parent2NodeId":"2550965664","Parent2NodeName":"Open de EE.UU. 2020","Parent2NodePriority":0,"Parent3NodeId":"634945983","Parent3NodeName":"Open de EE.UU.","Parent3NodePriority":0,"Parent4NodeId":"488485541","Parent4NodeName":"EE.UU.","Parent4NodePriority":0,"Parent5NodeId":"377374333","Parent5NodeName":"Golf","Parent5NodePriority":100,"Parent6NodeId":"-1","Parent6NodeName":null,"Parent6NodePriority":0,"EventNodeTypeId":12,"TypeFilterList":null}},{"Key":"2550967397","Value":{"Odd":100.0,"SortOrder":0,"Tax":"Tax1|0,00|S;Tax2|0,00|S","GameTypeResultsNr":-1,"ParentUniqueId":null,"Parent2UniqueId":null,"Parent3UniqueId":"16d74246-0ae1-4669-b9f0-7e88d9b7df4e","IsLive":false,"LastUpdated":"2020-06-25T08:00:20.5120701+02:00","NodeName":"Kevin Kisner","NodeId":"2550967397","Type":12,"IsActive":true,"SportHandle":"golf","Priority":0,"CountryCode":"","ParentNodeId":"2550967323","ParentNodeName":"Ganador","ParentNodePriority":0,"DisplayTypeName":"","Parent2NodeId":"2550965664","Parent2NodeName":"Open de EE.UU. 2020","Parent2NodePriority":0,"Parent3NodeId":"634945983","Parent3NodeName":"Open de EE.UU.","Parent3NodePriority":0,"Parent4NodeId":"488485541","Parent4NodeName":"EE.UU.","Parent4NodePriority":0,"Parent5NodeId":"377374333","Parent5NodeName":"Golf","Parent5NodePriority":100,"Parent6NodeId":"-1","Parent6NodeName":null,"Parent6NodePriority":0,"EventNodeTypeId":12,"TypeFilterList":null}},{"Key":"2550967398","Value":{"Odd":100.0,"SortOrder":0,"Tax":"Tax1|0,00|S;Tax2|0,00|S","GameTypeResultsNr":-1,"ParentUniqueId":null,"Parent2UniqueId":null,"Parent3UniqueId":"16d74246-0ae1-4669-b9f0-7e88d9b7df4e","IsLive":false,"LastUpdated":"2020-06-25T08:00:20.5120701+02:00","NodeName":"Ian Poulter","NodeId":"2550967398","Type":12,"IsActive":true,"SportHandle":"golf","Priority":0,"CountryCode":"","ParentNodeId":"2550967323","ParentNodeName":"Ganador","ParentNodePriority":0,"DisplayTypeName":"","Parent2NodeId":"2550965664","Parent2NodeName":"Open de EE.UU. 2020","Parent2NodePriority":0,"Parent3NodeId":"634945983","Parent3NodeName":"Open de EE.UU.","Parent3NodePriority":0,"Parent4NodeId":"488485541","Parent4NodeName":"EE.UU.","Parent4NodePriority":0,"Parent5NodeId":"377374333","Parent5NodeName":"Golf","Parent5NodePriority":100,"Parent6NodeId":"-1","Parent6NodeName":null,"Parent6NodePriority":0,"EventNodeTypeId":12,"TypeFilterList":null}},{"Key":"2550967399","Value":{"Odd":100.0,"SortOrder":0,"Tax":"Tax1|0,00|S;Tax2|0,00|S","GameTypeResultsNr":-1,"ParentUniqueId":null,"Parent2UniqueId":null,"Parent3UniqueId":"16d74246-0ae1-4669-b9f0-7e88d9b7df4e","IsLive":false,"LastUpdated":"2020-06-25T08:00:20.5120701+02:00","NodeName":"Alex Noren","NodeId":"2550967399","Type":12,"IsActive":true,"SportHandle":"golf","Priority":0,"CountryCode":"","ParentNodeId":"2550967323","ParentNodeName":"Ganador","ParentNodePriority":0,"DisplayTypeName":"","Parent2NodeId":"2550965664","Parent2NodeName":"Open de EE.UU. 2020","Parent2NodePriority":0,"Parent3NodeId":"634945983","Parent3NodeName":"Open de EE.UU.","Parent3NodePriority":0,"Parent4NodeId":"488485541","Parent4NodeName":"EE.UU.","Parent4NodePriority":0,"Parent5NodeId":"377374333","Parent5NodeName":"Golf","Parent5NodePriority":100,"Parent6NodeId":"-1","Parent6NodeName":null,"Parent6NodePriority":0,"EventNodeTypeId":12,"TypeFilterList":null}},{"Key":"2550967400","Value":{"Odd":100.0,"SortOrder":0,"Tax":"Tax1|0,00|S;Tax2|0,00|S","GameTypeResultsNr":-1,"ParentUniqueId":null,"Parent2UniqueId":null,"Parent3UniqueId":"16d74246-0ae1-4669-b9f0-7e88d9b7df4e","IsLive":false,"LastUpdated":"2020-06-25T08:00:20.5120701+02:00","NodeName":"Matthew Wolff","NodeId":"2550967400","Type":12,"IsActive":true,"SportHandle":"golf","Priority":0,"CountryCode":"","ParentNodeId":"2550967323","ParentNodeName":"Ganador","ParentNodePriority":0,"DisplayTypeName":"","Parent2NodeId":"2550965664","Parent2NodeName":"Open de EE.UU. 2020","Parent2NodePriority":0,"Parent3NodeId":"634945983","Parent3NodeName":"Open de EE.UU.","Parent3NodePriority":0,"Parent4NodeId":"488485541","Parent4NodeName":"EE.UU.","Parent4NodePriority":0,"Parent5NodeId":"377374333","Parent5NodeName":"Golf","Parent5NodePriority":100,"Parent6NodeId":"-1","Parent6NodeName":null,"Parent6NodePriority":0,"EventNodeTypeId":12,"TypeFilterList":null}},{"Key":"2550967401","Value":{"Odd":100.0,"SortOrder":0,"Tax":"Tax1|0,00|S;Tax2|0,00|S","GameTypeResultsNr":-1,"ParentUniqueId":null,"Parent2UniqueId":null,"Parent3UniqueId":"16d74246-0ae1-4669-b9f0-7e88d9b7df4e","IsLive":false,"LastUpdated":"2020-06-25T08:00:20.5120701+02:00","NodeName":"Branden Grace","NodeId":"2550967401","Type":12,"IsActive":true,"SportHandle":"golf","Priority":0,"CountryCode":"","ParentNodeId":"2550967323","ParentNodeName":"Ganador","ParentNodePriority":0,"DisplayTypeName":"","Parent2NodeId":"2550965664","Parent2NodeName":"Open de EE.UU. 2020","Parent2NodePriority":0,"Parent3NodeId":"634945983","Parent3NodeName":"Open de EE.UU.","Parent3NodePriority":0,"Parent4NodeId":"488485541","Parent4NodeName":"EE.UU.","Parent4NodePriority":0,"Parent5NodeId":"377374333","Parent5NodeName":"Golf","Parent5NodePriority":100,"Parent6NodeId":"-1","Parent6NodeName":null,"Parent6NodePriority":0,"EventNodeTypeId":12,"TypeFilterList":null}},{"Key":"2550967402","Value":{"Odd":100.0,"SortOrder":0,"Tax":"Tax1|0,00|S;Tax2|0,00|S","GameTypeResultsNr":-1,"ParentUniqueId":null,"Parent2UniqueId":null,"Parent3UniqueId":"16d74246-0ae1-4669-b9f0-7e88d9b7df4e","IsLive":false,"LastUpdated":"2020-06-25T08:00:20.5120701+02:00","NodeName":"Haotong Li","NodeId":"2550967402","Type":12,"IsActive":true,"SportHandle":"golf","Priority":0,"CountryCode":"","ParentNodeId":"2550967323","ParentNodeName":"Ganador","ParentNodePriority":0,"DisplayTypeName":"","Parent2NodeId":"2550965664","Parent2NodeName":"Open de EE.UU. 2020","Parent2NodePriority":0,"Parent3NodeId":"634945983","Parent3NodeName":"Open de EE.UU.","Parent3NodePriority":0,"Parent4NodeId":"488485541","Parent4NodeName":"EE.UU.","Parent4NodePriority":0,"Parent5NodeId":"377374333","Parent5NodeName":"Golf","Parent5NodePriority":100,"Parent6NodeId":"-1","Parent6NodeName":null,"Parent6NodePriority":0,"EventNodeTypeId":12,"TypeFilterList":null}},{"Key":"2550967403","Value":{"Odd":100.0,"SortOrder":0,"Tax":"Tax1|0,00|S;Tax2|0,00|S","GameTypeResultsNr":-1,"ParentUniqueId":null,"Parent2UniqueId":null,"Parent3UniqueId":"16d74246-0ae1-4669-b9f0-7e88d9b7df4e","IsLive":false,"LastUpdated":"2020-06-25T08:00:20.5120701+02:00","NodeName":"Billy Horschel","NodeId":"2550967403","Type":12,"IsActive":true,"SportHandle":"golf","Priority":0,"CountryCode":"","ParentNodeId":"2550967323","ParentNodeName":"Ganador","ParentNodePriority":0,"DisplayTypeName":"","Parent2NodeId":"2550965664","Parent2NodeName":"Open de EE.UU. 2020","Parent2NodePriority":0,"Parent3NodeId":"634945983","Parent3NodeName":"Open de EE.UU.","Parent3NodePriority":0,"Parent4NodeId":"488485541","Parent4NodeName":"EE.UU.","Parent4NodePriority":0,"Parent5NodeId":"377374333","Parent5NodeName":"Golf","Parent5NodePriority":100,"Parent6NodeId":"-1","Parent6NodeName":null,"Parent6NodePriority":0,"EventNodeTypeId":12,"TypeFilterList":null}},{"Key":"2550967404","Value":{"Odd":100.0,"SortOrder":0,"Tax":"Tax1|0,00|S;Tax2|0,00|S","GameTypeResultsNr":-1,"ParentUniqueId":null,"Parent2UniqueId":null,"Parent3UniqueId":"16d74246-0ae1-4669-b9f0-7e88d9b7df4e","IsLive":false,"LastUpdated":"2020-06-25T08:00:20.5120701+02:00","NodeName":"Keegan Bradley","NodeId":"2550967404","Type":12,"IsActive":true,"SportHandle":"golf","Priority":0,"CountryCode":"","ParentNodeId":"2550967323","ParentNodeName":"Ganador","ParentNodePriority":0,"DisplayTypeName":"","Parent2NodeId":"2550965664","Parent2NodeName":"Open de EE.UU. 2020","Parent2NodePriority":0,"Parent3NodeId":"634945983","Parent3NodeName":"Open de EE.UU.","Parent3NodePriority":0,"Parent4NodeId":"488485541","Parent4NodeName":"EE.UU.","Parent4NodePriority":0,"Parent5NodeId":"377374333","Parent5NodeName":"Golf","Parent5NodePriority":100,"Parent6NodeId":"-1","Parent6NodeName":null,"Parent6NodePriority":0,"EventNodeTypeId":12,"TypeFilterList":null}},{"Key":"2550967405","Value":{"Odd":125.0,"SortOrder":0,"Tax":"Tax1|0,00|S;Tax2|0,00|S","GameTypeResultsNr":-1,"ParentUniqueId":null,"Parent2UniqueId":null,"Parent3UniqueId":"16d74246-0ae1-4669-b9f0-7e88d9b7df4e","IsLive":false,"LastUpdated":"2020-06-25T08:00:20.5120701+02:00","NodeName":"J.B. Holmes","NodeId":"2550967405","Type":12,"IsActive":true,"SportHandle":"golf","Priority":0,"CountryCode":"","ParentNodeId":"2550967323","ParentNodeName":"Ganador","ParentNodePriority":0,"DisplayTypeName":"","Parent2NodeId":"2550965664","Parent2NodeName":"Open de EE.UU. 2020","Parent2NodePriority":0,"Parent3NodeId":"634945983","Parent3NodeName":"Open de EE.UU.","Parent3NodePriority":0,"Parent4NodeId":"488485541","Parent4NodeName":"EE.UU.","Parent4NodePriority":0,"Parent5NodeId":"377374333","Parent5NodeName":"Golf","Parent5NodePriority":100,"Parent6NodeId":"-1","Parent6NodeName":null,"Parent6NodePriority":0,"EventNodeTypeId":12,"TypeFilterList":null}},{"Key":"2550967406","Value":{"Odd":125.0,"SortOrder":0,"Tax":"Tax1|0,00|S;Tax2|0,00|S","GameTypeResultsNr":-1,"ParentUniqueId":null,"Parent2UniqueId":null,"Parent3UniqueId":"16d74246-0ae1-4669-b9f0-7e88d9b7df4e","IsLive":false,"LastUpdated":"2020-06-25T08:00:20.5120701+02:00","NodeName":"Eddie Pepperell","NodeId":"2550967406","Type":12,"IsActive":true,"SportHandle":"golf","Priority":0,"CountryCode":"","ParentNodeId":"2550967323","ParentNodeName":"Ganador","ParentNodePriority":0,"DisplayTypeName":"","Parent2NodeId":"2550965664","Parent2NodeName":"Open de EE.UU. 2020","Parent2NodePriority":0,"Parent3NodeId":"634945983","Parent3NodeName":"Open de EE.UU.","Parent3NodePriority":0,"Parent4NodeId":"488485541","Parent4NodeName":"EE.UU.","Parent4NodePriority":0,"Parent5NodeId":"377374333","Parent5NodeName":"Golf","Parent5NodePriority":100,"Parent6NodeId":"-1","Parent6NodeName":null,"Parent6NodePriority":0,"EventNodeTypeId":12,"TypeFilterList":null}},{"Key":"2550967407","Value":{"Odd":125.0,"SortOrder":0,"Tax":"Tax1|0,00|S;Tax2|0,00|S","GameTypeResultsNr":-1,"ParentUniqueId":null,"Parent2UniqueId":null,"Parent3UniqueId":"16d74246-0ae1-4669-b9f0-7e88d9b7df4e","IsLive":false,"LastUpdated":"2020-06-25T08:00:20.5120701+02:00","NodeName":"Thorbjorn Olesen","NodeId":"2550967407","Type":12,"IsActive":true,"SportHandle":"golf","Priority":0,"CountryCode":"","ParentNodeId":"2550967323","ParentNodeName":"Ganador","ParentNodePriority":0,"DisplayTypeName":"","Parent2NodeId":"2550965664","Parent2NodeName":"Open de EE.UU. 2020","Parent2NodePriority":0,"Parent3NodeId":"634945983","Parent3NodeName":"Open de EE.UU.","Parent3NodePriority":0,"Parent4NodeId":"488485541","Parent4NodeName":"EE.UU.","Parent4NodePriority":0,"Parent5NodeId":"377374333","Parent5NodeName":"Golf","Parent5NodePriority":100,"Parent6NodeId":"-1","Parent6NodeName":null,"Parent6NodePriority":0,"EventNodeTypeId":12,"TypeFilterList":null}}]