[{"Key":"2822346263","Value":{"LiveHistory":null,"IsLive":false,"StartDate":"2020-07-30T23:05:00Z","Participants":[{"Id":14835002,"IsHome":false,"LocalizedNames":{"LocalizedValues":[{"CountryCode":"-1","LanguageCode":"-1","Value":"Milwaukee Bucks"}],"ReferenceId":-1},"LocalizedShortNames":{"LocalizedValues":[{"CountryCode":"-1","LanguageCode":"-1","Value":"MBu"}],"ReferenceId":0}},{"Id":14835003,"IsHome":false,"LocalizedNames":{"LocalizedValues":[{"CountryCode":"-1","LanguageCode":"-1","Value":"Los Angeles Lakers"}],"ReferenceId":-1},"LocalizedShortNames":{"LocalizedValues":[{"CountryCode":"-1","LanguageCode":"-1","Value":"LAn"}],"ReferenceId":0}},{"Id":14835004,"IsHome":false,"LocalizedNames":{"LocalizedValues":[{"CountryCode":"-1","LanguageCode":"-1","Value":"Los Angeles Clippers"}],"ReferenceId":-1},"LocalizedShortNames":{"LocalizedValues":[{"CountryCode":"-1","LanguageCode":"-1","Value":"LAn"}],"ReferenceId":0}},{"Id":14835005,"IsHome":false,"LocalizedNames":{"LocalizedValues":[{"CountryCode":"-1","LanguageCode":"-1","Value":"Houston Rockets"}],"ReferenceId":-1},"LocalizedShortNames":{"LocalizedValues":[{"CountryCode":"-1","LanguageCode":"-1","Value":"HRo"}],"ReferenceId":0}},{"Id":14835006,"IsHome":false,"LocalizedNames":{"LocalizedValues":[{"CountryCode":"-1","LanguageCode":"-1","Value":"Denver Nuggets"}],"ReferenceId":-1},"LocalizedShortNames":{"LocalizedValues":[{"CountryCode":"-1","LanguageCode":"-1","Value":"DNu"}],"ReferenceId":0}},{"Id":14835007,"IsHome":false,"LocalizedNames":{"LocalizedValues":[{"CountryCode":"-1","LanguageCode":"-1","Value":"Boston Celtics"}],"ReferenceId":-1},"LocalizedShortNames":{"LocalizedValues":[{"CountryCode":"-1","LanguageCode":"-1","Value":"BCe"}],"ReferenceId":0}},{"Id":14835008,"IsHome":false,"LocalizedNames":{"LocalizedValues":[{"CountryCode":"-1","LanguageCode":"-1","Value":"Philadelphia 76ers"}],"ReferenceId":-1},"LocalizedShortNames":{"LocalizedValues":[{"CountryCode":"-1","LanguageCode":"-1","Value":"Per"}],"ReferenceId":0}},{"Id":14835009,"IsHome":false,"LocalizedNames":{"LocalizedValues":[{"CountryCode":"-1","LanguageCode":"-1","Value":"Utah Jazz"}],"ReferenceId":-1},"LocalizedShortNames":{"LocalizedValues":[{"CountryCode":"-1","LanguageCode":"-1","Value":"UJa"}],"ReferenceId":0}},{"Id":14835010,"IsHome":false,"LocalizedNames":{"LocalizedValues":[{"CountryCode":"-1","LanguageCode":"-1","Value":"Miami Heat"}],"ReferenceId":-1},"LocalizedShortNames":{"LocalizedValues":[{"CountryCode":"-1","LanguageCode":"-1","Value":"MHe"}],"ReferenceId":0}},{"Id":14835011,"IsHome":false,"LocalizedNames":{"LocalizedValues":[{"CountryCode":"-1","LanguageCode":"-1","Value":"Toronto Raptors"}],"ReferenceId":-1},"LocalizedShortNames":{"LocalizedValues":[{"CountryCode":"-1","LanguageCode":"-1","Value":"TRa"}],"ReferenceId":0}},{"Id":14835012,"IsHome":false,"LocalizedNames":{"LocalizedValues":[{"CountryCode":"-1","LanguageCode":"-1","Value":"Dallas Mavericks"}],"ReferenceId":-1},"LocalizedShortNames":{"LocalizedValues":[{"CountryCode":"-1","LanguageCode":"-1","Value":"DMa"}],"ReferenceId":0}},{"Id":14835013,"IsHome":false,"LocalizedNames":{"LocalizedValues":[{"CountryCode":"-1","LanguageCode":"-1","Value":"Indiana Pacers"}],"ReferenceId":-1},"LocalizedShortNames":{"LocalizedValues":[{"CountryCode":"-1","LanguageCode":"-1","Value":"IPa"}],"ReferenceId":0}},{"Id":14835014,"IsHome":false,"LocalizedNames":{"LocalizedValues":[{"CountryCode":"-1","LanguageCode":"-1","Value":"Brooklyn Nets"}],"ReferenceId":-1},"LocalizedShortNames":{"LocalizedValues":[{"CountryCode":"-1","LanguageCode":"-1","Value":"BNe"}],"ReferenceId":0}},{"Id":14835015,"IsHome":false,"LocalizedNames":{"LocalizedValues":[{"CountryCode":"-1","LanguageCode":"-1","Value":"Oklahoma City Thunder"}],"ReferenceId":-1},"LocalizedShortNames":{"LocalizedValues":[{"CountryCode":"-1","LanguageCode":"-1","Value":"OCi"}],"ReferenceId":0}},{"Id":14835016,"IsHome":false,"LocalizedNames":{"LocalizedValues":[{"CountryCode":"-1","LanguageCode":"-1","Value":"New Orleans Pelicans"}],"ReferenceId":-1},"LocalizedShortNames":{"LocalizedValues":[{"CountryCode":"-1","LanguageCode":"-1","Value":"NOr"}],"ReferenceId":0}},{"Id":14835017,"IsHome":false,"LocalizedNames":{"LocalizedValues":[{"CountryCode":"-1","LanguageCode":"-1","Value":"Portland Trail Blazers"}],"ReferenceId":-1},"LocalizedShortNames":{"LocalizedValues":[{"CountryCode":"-1","LanguageCode":"-1","Value":"PTr"}],"ReferenceId":0}},{"Id":14835018,"IsHome":false,"LocalizedNames":{"LocalizedValues":[{"CountryCode":"-1","LanguageCode":"-1","Value":"Orlando Magic"}],"ReferenceId":-1},"LocalizedShortNames":{"LocalizedValues":[{"CountryCode":"-1","LanguageCode":"-1","Value":"OMa"}],"ReferenceId":0}},{"Id":14835019,"IsHome":false,"LocalizedNames":{"LocalizedValues":[{"CountryCode":"-1","LanguageCode":"-1","Value":"Memphis Grizzlies"}],"ReferenceId":-1},"LocalizedShortNames":{"LocalizedValues":[{"CountryCode":"-1","LanguageCode":"-1","Value":"MGr"}],"ReferenceId":0}},{"Id":14835020,"IsHome":false,"LocalizedNames":{"LocalizedValues":[{"CountryCode":"-1","LanguageCode":"-1","Value":"San Antonio Spurs"}],"ReferenceId":-1},"LocalizedShortNames":{"LocalizedValues":[{"CountryCode":"-1","LanguageCode":"-1","Value":"SAn"}],"ReferenceId":0}},{"Id":14835021,"IsHome":false,"LocalizedNames":{"LocalizedValues":[{"CountryCode":"-1","LanguageCode":"-1","Value":"Sacramento Kings"}],"ReferenceId":-1},"LocalizedShortNames":{"LocalizedValues":[{"CountryCode":"-1","LanguageCode":"-1","Value":"SKi"}],"ReferenceId":0}},{"Id":14835022,"IsHome":false,"LocalizedNames":{"LocalizedValues":[{"CountryCode":"-1","LanguageCode":"-1","Value":"Washington Wizards"}],"ReferenceId":-1},"LocalizedShortNames":{"LocalizedValues":[{"CountryCode":"-1","LanguageCode":"-1","Value":"WWi"}],"ReferenceId":0}},{"Id":14835023,"IsHome":false,"LocalizedNames":{"LocalizedValues":[{"CountryCode":"-1","LanguageCode":"-1","Value":"Phoenix Suns"}],"ReferenceId":-1},"LocalizedShortNames":{"LocalizedValues":[{"CountryCode":"-1","LanguageCode":"-1","Value":"PSu"}],"ReferenceId":0}}],"IsActive":true,"SmartMarketReferenceGameTypeIds":"","ParentUniqueId":"8610ff0f-8750-429c-8c3d-0938ff2f2f43","Parent2UniqueId":null,"Parent3UniqueId":null,"LastUpdated":"2020-06-25T08:00:18.1370585+02:00","NodeName":"NBA 2019/2020 - Campeonato NBA (Play-Off Incluido)","NodeId":"2822346263","Type":10,"SportHandle":"basketball","Priority":9980,"CountryCode":"","ParentNodeId":"461719819","ParentNodeName":"Apuestas Anticipadas - NBA","ParentNodePriority":9980,"DisplayTypeName":"","Parent2NodeId":"358491826","Parent2NodeName":"EE.UU.","Parent2NodePriority":9900,"Parent3NodeId":"358491795","Parent3NodeName":"Baloncesto","Parent3NodePriority":10,"Parent4NodeId":"-1","Parent4NodeName":null,"Parent4NodePriority":0,"Parent5NodeId":"-1","Parent5NodeName":null,"Parent5NodePriority":0,"Parent6NodeId":"-1","Parent6NodeName":null,"Parent6NodePriority":0,"EventNodeTypeId":10,"TypeFilterList":null}},{"Key":"2822347508","Value":{"SpecialOddsValue":"","CategoryInfo":{"CategoryId":"90","CategoryName":"Apuestas Anticipadas","IsRelevant":true},"CategoryInfos":[{"CategoryId":"90","CategoryName":"Apuestas Anticipadas","IsRelevant":true}],"LocalizedCategoryInfos":{"-1":[{"CategoryId":"90","CategoryName":"Apuestas Anticipadas","IsRelevant":true}]},"StartDate":"2020-07-30T23:05:00Z","GameTypeId":303,"SmartMarketAvailable":false,"ParentUniqueId":null,"Parent2UniqueId":"8610ff0f-8750-429c-8c3d-0938ff2f2f43","Parent3UniqueId":null,"IsLive":false,"LastUpdated":"2020-06-25T08:00:18.1370585+02:00","NodeName":"Ganador","NodeId":"2822347508","Type":11,"IsActive":true,"SportHandle":"basketball","Priority":9980,"CountryCode":"","ParentNodeId":"2822346263","ParentNodeName":"NBA 2019/2020 - Campeonato NBA (Play-Off Incluido)","ParentNodePriority":9980,"DisplayTypeName":"outrightlist","Parent2NodeId":"461719819","Parent2NodeName":"Apuestas Anticipadas - NBA","Parent2NodePriority":9980,"Parent3NodeId":"358491826","Parent3NodeName":"EE.UU.","Parent3NodePriority":9900,"Parent4NodeId":"358491795","Parent4NodeName":"Baloncesto","Parent4NodePriority":10,"Parent5NodeId":"-1","Parent5NodeName":null,"Parent5NodePriority":0,"Parent6NodeId":"-1","Parent6NodeName":null,"Parent6NodePriority":0,"EventNodeTypeId":11,"TypeFilterList":null}},{"Key":"2822347515","Value":{"Odd":3.25,"SortOrder":0,"Tax":"Tax1|0,00|S;Tax2|0,00|S","GameTypeResultsNr":-1,"ParentUniqueId":null,"Parent2UniqueId":null,"Parent3UniqueId":"8610ff0f-8750-429c-8c3d-0938ff2f2f43","IsLive":false,"LastUpdated":"2020-06-25T08:00:20.8089325+02:00","NodeName":"Milwaukee Bucks","NodeId":"2822347515","Type":12,"IsActive":true,"SportHandle":"basketball","Priority":0,"CountryCode":"","ParentNodeId":"2822347508","ParentNodeName":"Ganador","ParentNodePriority":9980,"DisplayTypeName":"","Parent2NodeId":"2822346263","Parent2NodeName":"NBA 2019/2020 - Campeonato NBA (Play-Off Incluido)","Parent2NodePriority":9980,"Parent3NodeId":"461719819","Parent3NodeName":"Apuestas Anticipadas - NBA","Parent3NodePriority":9980,"Parent4NodeId":"358491826","Parent4NodeName":"EE.UU.","Parent4NodePriority":9900,"Parent5NodeId":"358491795","Parent5NodeName":"Baloncesto","Parent5NodePriority":10,"Parent6NodeId":"-1","Parent6NodeName":null,"Parent6NodePriority":0,"EventNodeTypeId":12,"TypeFilterList":null}},{"Key":"2822347516","Value":{"Odd":3.5,"SortOrder":0,"Tax":"Tax1|0,00|S;Tax2|0,00|S","GameTypeResultsNr":-1,"ParentUniqueId":null,"Parent2UniqueId":null,"Parent3UniqueId":"8610ff0f-8750-429c-8c3d-0938ff2f2f43","IsLive":false,"LastUpdated":"2020-06-25T08:00:20.8089325+02:00","NodeName":"Los Angeles Lakers","NodeId":"2822347516","Type":12,"IsActive":true,"SportHandle":"basketball","Priority":0,"CountryCode":"","ParentNodeId":"2822347508","ParentNodeName":"Ganador","ParentNodePriority":9980,"DisplayTypeName":"","Parent2NodeId":"2822346263","Parent2NodeName":"NBA 2019/2020 - Campeonato NBA (Play-Off Incluido)","Parent2NodePriority":9980,"Parent3NodeId":"461719819","Parent3NodeName":"Apuestas Anticipadas - NBA","Parent3NodePriority":9980,"Parent4NodeId":"358491826","Parent4NodeName":"EE.UU.","Parent4NodePriority":9900,"Parent5NodeId":"358491795","Parent5NodeName":"Baloncesto","Parent5NodePriority":10,"Parent6NodeId":"-1","Parent6NodeName":null,"Parent6NodePriority":0,"EventNodeTypeId":12,"TypeFilterList":null}},{"Key":"2822347517","Value":{"Odd":4.0,"SortOrder":0,"Tax":"Tax1|0,00|S;Tax2|0,00|S","GameTypeResultsNr":-1,"ParentUniqueId":null,"Parent2UniqueId":null,"Parent3UniqueId":"8610ff0f-8750-429c-8c3d-0938ff2f2f43","IsLive":false,"LastUpdated":"2020-06-25T08:00:20.8089325+02:00","NodeName":"Los Angeles Clippers","NodeId":"2822347517","Type":12,"IsActive":true,"SportHandle":"basketball","Priority":0,"CountryCode":"","ParentNodeId":"2822347508","ParentNodeName":"Ganador","ParentNodePriority":9980,"DisplayTypeName":"","Parent2NodeId":"2822346263","Parent2NodeName":"NBA 2019/2020 - Campeonato NBA (Play-Off Incluido)","Parent2NodePriority":9980,"Parent3NodeId":"461719819","Parent3NodeName":"Apuestas Anticipadas - NBA","Parent3NodePriority":9980,"Parent4NodeId":"358491826","Parent4NodeName":"EE.UU.","Parent4NodePriority":9900,"Parent5NodeId":"358491795","Parent5NodeName":"Baloncesto","Parent5NodePriority":10,"Parent6NodeId":"-1","Parent6NodeName":null,"Parent6NodePriority":0,"EventNodeTypeId":12,"TypeFilterList":null}},{"Key":"2822347518","Value":{"Odd":12.0,"SortOrder":0,"Tax":"Tax1|0,00|S;Tax2|0,00|S","GameTypeResultsNr":-1,"ParentUniqueId":null,"Parent2UniqueId":null,"Parent3UniqueId":"8610ff0f-8750-429c-8c3d-0938ff2f2f43","IsLive":false,"LastUpdated":"2020-06-25T08:00:20.8089325+02:00","NodeName":"Houston Rockets","NodeId":"2822347518","Type":12,"IsActive":true,"SportHandle":"basketball","Priority":0,"CountryCode":"","ParentNodeId":"2822347508","ParentNodeName":"Ganador","ParentNodePriority":9980,"DisplayTypeName":"","Parent2NodeId":"2822346263","Parent2NodeName":"NBA 2019/2020 - Campeonato NBA (Play-Off Incluido)","Parent2NodePriority":9980,"Parent3NodeId":"461719819","Parent3NodeName":"Apuestas Anticipadas - NBA","Parent3NodePriority":9980,"Parent4NodeId":"358491826","Parent4NodeName":"EE.UU.","Parent4NodePriority":9900,"Parent5NodeId":"358491795","Parent5NodeName":"Baloncesto","Parent5NodePriority":10,"Parent6NodeId":"-1","Parent6NodeName":null,"Parent6NodePriority":0,"EventNodeTypeId":12,"TypeFilterList":null}},{"Key":"2822347519","Value":{"Odd":15.0,"SortOrder":0,"Tax":"Tax1|0,00|S;Tax2|0,00|S","GameTypeResultsNr":-1,"ParentUniqueId":null,"Parent2UniqueId":null,"Parent3UniqueId":"8610ff0f-8750-429c-8c3d-0938ff2f2f43","IsLive":false,"LastUpdated":"2020-06-25T08:00:20.8089325+02:00","NodeName":"Denver Nuggets","NodeId":"2822347519","Type":12,"IsActive":true,"SportHandle":"basketball","Priority":0,"CountryCode":"","ParentNodeId":"2822347508","ParentNodeName":"Ganador","ParentNodePriority":9980,"DisplayTypeName":"","Parent2NodeId":"2822346263","Parent2NodeName":"NBA 2019/2020 - Campeonato NBA (Play-Off Incluido)","Parent2NodePriority":9980,"Parent3NodeId":"461719819","Parent3NodeName":"Apuestas Anticipadas - NBA","Parent3NodePriority":9980,"Parent4NodeId":"358491826","Parent4NodeName":"EE.UU.","Parent4NodePriority":9900,"Parent5NodeId":"358491795","Parent5NodeName":"Baloncesto","Parent5NodePriority":10,"Parent6NodeId":"-1","Parent6NodeName":null,"Parent6NodePriority":0,"EventNodeTypeId":12,"TypeFilterList":null}},{"Key":"2822347520","Value":{"Odd":18.0,"SortOrder":0,"Tax":"Tax1|0,00|S;Tax2|0,00|S","GameTypeResultsNr":-1,"ParentUniqueId":null,"Parent2UniqueId":null,"Parent3UniqueId":"8610ff0f-8750-429c-8c3d-0938ff2f2f43","IsLive":false,"LastUpdated":"2020-06-25T08:00:20.8089325+02:00","NodeName":"Boston Celtics","NodeId":"2822347520","Type":12,"IsActive":true,"SportHandle":"basketball","Priority":0,"CountryCode":"","ParentNodeId":"2822347508","ParentNodeName":"Ganador","ParentNodePriority":9980,"DisplayTypeName":"","Parent2NodeId":"2822346263","Parent2NodeName":"NBA 2019/2020 - Campeonato NBA (Play-Off Incluido)","Parent2NodePriority":9980,"Parent3NodeId":"461719819","Parent3NodeName":"Apuestas Anticipadas - NBA","Parent3NodePriority":9980,"Parent4NodeId":"358491826","Parent4NodeName":"EE.UU.","Parent4NodePriority":9900,"Parent5NodeId":"358491795","Parent5NodeName":"Baloncesto","Parent5NodePriority":10,"Parent6NodeId":"-1","Parent6NodeName":null,"Parent6NodePriority":0,"EventNodeTypeId":12,"TypeFilterList":null}},{"Key":"2822347521","Value":{"Odd":18.0,"SortOrder":0,"Tax":"Tax1|0,00|S;Tax2|0,00|S","GameTypeResultsNr":-1,"ParentUniqueId":null,"Parent2UniqueId":null,"Parent3UniqueId":"8610ff0f-8750-429c-8c3d-0938ff2f2f43","IsLive":false,"LastUpdated":"2020-06-25T08:00:20.8089325+02:00","NodeName":"Philadelphia 76ers","NodeId":"2822347521","Type":12,"IsActive":true,"SportHandle":"basketball","Priority":0,"CountryCode":"","ParentNodeId":"2822347508","ParentNodeName":"Ganador","ParentNodePriority":9980,"DisplayTypeName":"","Parent2NodeId":"2822346263","Parent2NodeName":"NBA 2019/2020 - Campeonato NBA (Play-Off Incluido)","Parent2NodePriority":9980,"Parent3NodeId":"461719819","Parent3NodeName":"Apuestas Anticipadas - NBA","Parent3NodePriority":9980,"Parent4NodeId":"358491826","Parent4NodeName":"EE.UU.","Parent4NodePriority":9900,"Parent5NodeId":"358491795","Parent5NodeName":"Baloncesto","Parent5NodePriority":10,"Parent6NodeId":"-1","Parent6NodeName":null,"Parent6NodePriority":0,"EventNodeTypeId":12,"TypeFilterList":null}},{"Key":"2822347522","Value":{"Odd":20.0,"SortOrder":0,"Tax":"Tax1|0,00|S;Tax2|0,00|S","GameTypeResultsNr":-1,"ParentUniqueId":null,"Parent2UniqueId":null,"Parent3UniqueId":"8610ff0f-8750-429c-8c3d-0938ff2f2f43","IsLive":false,"LastUpdated":"2020-06-25T08:00:20.8089325+02:00","NodeName":"Utah Jazz","NodeId":"2822347522","Type":12,"IsActive":true,"SportHandle":"basketball","Priority":0,"CountryCode":"","ParentNodeId":"2822347508","ParentNodeName":"Ganador","ParentNodePriority":9980,"DisplayTypeName":"","Parent2NodeId":"2822346263","Parent2NodeName":"NBA 2019/2020 - Campeonato NBA (Play-Off Incluido)","Parent2NodePriority":9980,"Parent3NodeId":"461719819","Parent3NodeName":"Apuestas Anticipadas - NBA","Parent3NodePriority":9980,"Parent4NodeId":"358491826","Parent4NodeName":"EE.UU.","Parent4NodePriority":9900,"Parent5NodeId":"358491795","Parent5NodeName":"Baloncesto","Parent5NodePriority":10,"Parent6NodeId":"-1","Parent6NodeName":null,"Parent6NodePriority":0,"EventNodeTypeId":12,"TypeFilterList":null}},{"Key":"2822347523","Value":{"Odd":20.0,"SortOrder":0,"Tax":"Tax1|0,00|S;Tax2|0,00|S","GameTypeResultsNr":-1,"ParentUniqueId":null,"Parent2UniqueId":null,"Parent3UniqueId":"8610ff0f-8750-429c-8c3d-0938ff2f2f43","IsLive":false,"LastUpdated":"2020-06-25T08:00:20.8089325+02:00","NodeName":"Miami Heat","NodeId":"2822347523","Type":12,"IsActive":true,"SportHandle":"basketball","Priority":0,"CountryCode":"","ParentNodeId":"2822347508","ParentNodeName":"Ganador","ParentNodePriority":9980,"DisplayTypeName":"","Parent2NodeId":"2822346263","Parent2NodeName":"NBA 2019/2020 - Campeonato NBA (Play-Off Incluido)","Parent2NodePriority":9980,"Parent3NodeId":"461719819","Parent3NodeName":"Apuestas Anticipadas - NBA","Parent3NodePriority":9980,"Parent4NodeId":"358491826","Parent4NodeName":"EE.UU.","Parent4NodePriority":9900,"Parent5NodeId":"358491795","Parent5NodeName":"Baloncesto","Parent5NodePriority":10,"Parent6NodeId":"-1","Parent6NodeName":null,"Parent6NodePriority":0,"EventNodeTypeId":12,"TypeFilterList":null}},{"Key":"2822347524","Value":{"Odd":20.0,"SortOrder":0,"Tax":"Tax1|0,00|S;Tax2|0,00|S","GameTypeResultsNr":-1,"ParentUniqueId":null,"Parent2UniqueId":null,"Parent3UniqueId":"8610ff0f-8750-429c-8c3d-0938ff2f2f43","IsLive":false,"LastUpdated":"2020-06-25T08:00:20.8089325+02:00","NodeName":"Toronto Raptors","NodeId":"2822347524","Type":12,"IsActive":true,"SportHandle":"basketball","Priority":0,"CountryCode":"","ParentNodeId":"2822347508","ParentNodeName":"Ganador","ParentNodePriority":9980,"DisplayTypeName":"","Parent2NodeId":"2822346263","Parent2NodeName":"NBA 2019/2020 - Campeonato NBA (Play-Off Incluido)","Parent2NodePriority":9980,"Parent3NodeId":"461719819","Parent3NodeName":"Apuestas Anticipadas - NBA","Parent3NodePriority":9980,"Parent4NodeId":"358491826","Parent4NodeName":"EE.UU.","Parent4NodePriority":9900,"Parent5NodeId":"358491795","Parent5NodeName":"Baloncesto","Parent5NodePriority":10,"Parent6NodeId":"-1","Parent6NodeName":null,"Parent6NodePriority":0,"EventNodeTypeId":12,"TypeFilterList":null}},{"Key":"2822347525","Value":{"Odd":30.0,"SortOrder":0,"Tax":"Tax1|0,00|S;Tax2|0,00|S","GameTypeResultsNr":-1,"ParentUniqueId":null,"Parent2UniqueId":null,"Parent3UniqueId":"8610ff0f-8750-429c-8c3d-0938ff2f2f43","IsLive":false,"LastUpdated":"2020-06-25T08:00:20.8089325+02:00","NodeName":"Dallas Mavericks","NodeId":"2822347525","Type":12,"IsActive":true,"SportHandle":"basketball","Priority":0,"CountryCode":"","ParentNodeId":"2822347508","ParentNodeName":"Ganador","ParentNodePriority":9980,"DisplayTypeName":"","Parent2NodeId":"2822346263","Parent2NodeName":"NBA 2019/2020 - Campeonato NBA (Play-Off Incluido)","Parent2NodePriority":9980,"Parent3NodeId":"461719819","Parent3NodeName":"Apuestas Anticipadas - NBA","Parent3NodePriority":9980,"Parent4NodeId":"358491826","Parent4NodeName":"EE.UU.","Parent4NodePriority":9900,"Parent5NodeId":"358491795","Parent5NodeName":"Baloncesto","Parent5NodePriority":10,"Parent6NodeId":"-1","Parent6NodeName":null,"Parent6NodePriority":0,"EventNodeTypeId":12,"TypeFilterList":null}},{"Key":"2822347526","Value":{"Odd":40.0,"SortOrder":0,"Tax":"Tax1|0,00|S;Tax2|0,00|S","GameTypeResultsNr":-1,"ParentUniqueId":null,"Parent2UniqueId":null,"Parent3UniqueId":"8610ff0f-8750-429c-8c3d-0938ff2f2f43","IsLive":false,"LastUpdated":"2020-06-25T08:00:20.8089325+02:00","NodeName":"Indiana Pacers","NodeId":"2822347526","Type":12,"IsActive":true,"SportHandle":"basketball","Priority":0,"CountryCode":"","ParentNodeId":"2822347508","ParentNodeName":"Ganador","ParentNodePriority":9980,"DisplayTypeName":"","Parent2NodeId":"2822346263","Parent2NodeName":"NBA 2019/2020 - Campeonato NBA (Play-Off Incluido)","Parent2NodePriority":9980,"Parent3NodeId":"461719819","Parent3NodeName":"Apuestas Anticipadas - NBA","Parent3NodePriority":9980,"Parent4NodeId":"358491826","Parent4NodeName":"EE.UU.","Parent4NodePriority":9900,"Parent5NodeId":"358491795","Parent5NodeName":"Baloncesto","Parent5NodePriority":10,"Parent6NodeId":"-1","Parent6NodeName":null,"Parent6NodePriority":0,"EventNodeTypeId":12,"TypeFilterList":null}},{"Key":"2822347527","Value":{"Odd":40.0,"SortOrder":0,"Tax":"Tax1|0,00|S;Tax2|0,00|S","GameTypeResultsNr":-1,"ParentUniqueId":null,"Parent2UniqueId":null,"Parent3UniqueId":"8610ff0f-8750-429c-8c3d-0938ff2f2f43","IsLive":false,"LastUpdated":"2020-06-25T08:00:20.8089325+02:00","NodeName":"Brooklyn Nets","NodeId":"2822347527","Type":12,"IsActive":true,"SportHandle":"basketball","Priority":0,"CountryCode":"","ParentNodeId":"2822347508","ParentNodeName":"Ganador","ParentNodePriority":9980,"DisplayTypeName":"","Parent2NodeId":"2822346263","Parent2NodeName":"NBA 2019/2020 - Campeonato NBA (Play-Off Incluido)","Parent2NodePriority":9980,"Parent3NodeId":"461719819","Parent3NodeName":"Apuestas Anticipadas - NBA","Parent3NodePriority":9980,"Parent4NodeId":"358491826","Parent4NodeName":"EE.UU.","Parent4NodePriority":9900,"Parent5NodeId":"358491795","Parent5NodeName":"Baloncesto","Parent5NodePriority":10,"Parent6NodeId":"-1","Parent6NodeName":null,"Parent6NodePriority":0,"EventNodeTypeId":12,"TypeFilterList":null}},{"Key":"2822347528","Value":{"Odd":70.0,"SortOrder":0,"Tax":"Tax1|0,00|S;Tax2|0,00|S","GameTypeResultsNr":-1,"ParentUniqueId":null,"Parent2UniqueId":null,"Parent3UniqueId":"8610ff0f-8750-429c-8c3d-0938ff2f2f43","IsLive":false,"LastUpdated":"2020-06-25T08:00:20.8089325+02:00","NodeName":"Oklahoma City Thunder","NodeId":"2822347528","Type":12,"IsActive":true,"SportHandle":"basketball","Priority":0,"CountryCode":"","ParentNodeId":"2822347508","ParentNodeName":"Ganador","ParentNodePriority":9980,"DisplayTypeName":"","Parent2NodeId":"2822346263","Parent2NodeName":"NBA 2019/2020 - Campeonato NBA (Play-Off Incluido)","Parent2NodePriority":9980,"Parent3NodeId":"461719819","Parent3NodeName":"Apuestas Anticipadas - NBA","Parent3NodePriority":9980,"Parent4NodeId":"358491826","Parent4NodeName":"EE.UU.","Parent4NodePriority":9900,"Parent5NodeId":"358491795","Parent5NodeName":"Baloncesto","Parent5NodePriority":10,"Parent6NodeId":"-1","Parent6NodeName":null,"Parent6NodePriority":0,"EventNodeTypeId":12,"TypeFilterList":null}},{"Key":"2822347529","Value":{"Odd":100.0,"SortOrder":0,"Tax":"Tax1|0,00|S;Tax2|0,00|S","GameTypeResultsNr":-1,"ParentUniqueId":null,"Parent2UniqueId":null,"Parent3UniqueId":"8610ff0f-8750-429c-8c3d-0938ff2f2f43","IsLive":false,"LastUpdated":"2020-06-25T08:00:20.8089325+02:00","NodeName":"New Orleans Pelicans","NodeId":"2822347529","Type":12,"IsActive":true,"SportHandle":"basketball","Priority":0,"CountryCode":"","ParentNodeId":"2822347508","ParentNodeName":"Ganador","ParentNodePriority":9980,"DisplayTypeName":"","Parent2NodeId":"2822346263","Parent2NodeName":"NBA 2019/2020 - Campeonato NBA (Play-Off Incluido)","Parent2NodePriority":9980,"Parent3NodeId":"461719819","Parent3NodeName":"Apuestas Anticipadas - NBA","Parent3NodePriority":9980,"Parent4NodeId":"358491826","Parent4NodeName":"EE.UU.","Parent4NodePriority":9900,"Parent5NodeId":"358491795","Parent5NodeName":"Baloncesto","Parent5NodePriority":10,"Parent6NodeId":"-1","Parent6NodeName":null,"Parent6NodePriority":0,"EventNodeTypeId":12,"TypeFilterList":null}},{"Key":"2822347530","Value":{"Odd":150.0,"SortOrder":0,"Tax":"Tax1|0,00|S;Tax2|0,00|S","GameTypeResultsNr":-1,"ParentUniqueId":null,"Parent2UniqueId":null,"Parent3UniqueId":"8610ff0f-8750-429c-8c3d-0938ff2f2f43","IsLive":false,"LastUpdated":"2020-06-25T08:00:20.8089325+02:00","NodeName":"Portland Trail Blazers","NodeId":"2822347530","Type":12,"IsActive":true,"SportHandle":"basketball","Priority":0,"CountryCode":"","ParentNodeId":"2822347508","ParentNodeName":"Ganador","ParentNodePriority":9980,"DisplayTypeName":"","Parent2NodeId":"2822346263","Parent2NodeName":"NBA 2019/2020 - Campeonato NBA (Play-Off Incluido)","Parent2NodePriority":9980,"Parent3NodeId":"461719819","Parent3NodeName":"Apuestas Anticipadas - NBA","Parent3NodePriority":9980,"Parent4NodeId":"358491826","Parent4NodeName":"EE.UU.","Parent4NodePriority":9900,"Parent5NodeId":"358491795","Parent5NodeName":"Baloncesto","Parent5NodePriority":10,"Parent6NodeId":"-1","Parent6NodeName":null,"Parent6NodePriority":0,"EventNodeTypeId":12,"TypeFilterList":null}},{"Key":"2822347531","Value":{"Odd":150.0,"SortOrder":0,"Tax":"Tax1|0,00|S;Tax2|0,00|S","GameTypeResultsNr":-1,"ParentUniqueId":null,"Parent2UniqueId":null,"Parent3UniqueId":"8610ff0f-8750-429c-8c3d-0938ff2f2f43","IsLive":false,"LastUpdated":"2020-06-25T08:00:20.8089325+02:00","NodeName":"Orlando Magic","NodeId":"2822347531","Type":12,"IsActive":true,"SportHandle":"basketball","Priority":0,"CountryCode":"","ParentNodeId":"2822347508","ParentNodeName":"Ganador","ParentNodePriority":9980,"DisplayTypeName":"","Parent2NodeId":"2822346263","Parent2NodeName":"NBA 2019/2020 - Campeonato NBA (Play-Off Incluido)","Parent2NodePriority":9980,"Parent3NodeId":"461719819","Parent3NodeName":"Apuestas Anticipadas - NBA","Parent3NodePriority":9980,"Parent4NodeId":"358491826","Parent4NodeName":"EE.UU.","Parent4NodePriority":9900,"Parent5NodeId":"358491795","Parent5NodeName":"Baloncesto","Parent5NodePriority":10,"Parent6NodeId":"-1","Parent6NodeName":null,"Parent6NodePriority":0,"EventNodeTypeId":12,"TypeFilterList":null}},{"Key":"2822347532","Value":{"Odd":150.0,"SortOrder":0,"Tax":"Tax1|0,00|S;Tax2|0,00|S","GameTypeResultsNr":-1,"ParentUniqueId":null,"Parent2UniqueId":null,"Parent3UniqueId":"8610ff0f-8750-429c-8c3d-0938ff2f2f43","IsLive":false,"LastUpdated":"2020-06-25T08:00:20.8089325+02:00","NodeName":"Memphis Grizzlies","NodeId":"2822347532","Type":12,"IsActive":true,"SportHandle":"basketball","Priority":0,"CountryCode":"","ParentNodeId":"2822347508","ParentNodeName":"Ganador","ParentNodePriority":9980,"DisplayTypeName":"","Parent2NodeId":"2822346263","Parent2NodeName":"NBA 2019/2020 - Campeonato NBA (Play-Off Incluido)","Parent2NodePriority":9980,"Parent3NodeId":"461719819","Parent3NodeName":"Apuestas Anticipadas - NBA","Parent3NodePriority":9980,"Parent4NodeId":"358491826","Parent4NodeName":"EE.UU.","Parent4NodePriority":9900,"Parent5NodeId":"358491795","Parent5NodeName":"Baloncesto","Parent5NodePriority":10,"Parent6NodeId":"-1","Parent6NodeName":null,"Parent6NodePriority":0,"EventNodeTypeId":12,"TypeFilterList":null}},{"Key":"2822347533","Value":{"Odd":200.0,"SortOrder":0,"Tax":"Tax1|0,00|S;Tax2|0,00|S","GameTypeResultsNr":-1,"ParentUniqueId":null,"Parent2UniqueId":null,"Parent3UniqueId":"8610ff0f-8750-429c-8c3d-0938ff2f2f43","IsLive":false,"LastUpdated":"2020-06-25T08:00:20.8089325+02:00","NodeName":"San Antonio Spurs","NodeId":"2822347533","Type":12,"IsActive":true,"SportHandle":"basketball","Priority":0,"CountryCode":"","ParentNodeId":"2822347508","ParentNodeName":"Ganador","ParentNodePriority":9980,"DisplayTypeName":"","Parent2NodeId":"2822346263","Parent2NodeName":"NBA 2019/2020 - Campeonato NBA (Play-Off Incluido)","Parent2NodePriority":9980,"Parent3NodeId":"461719819","Parent3NodeName":"Apuestas Anticipadas - NBA","Parent3NodePriority":9980,"Parent4NodeId":"358491826","Parent4NodeName":"EE.UU.","Parent4NodePriority":9900,"Parent5NodeId":"358491795","Parent5NodeName":"Baloncesto","Parent5NodePriority":10,"Parent6NodeId":"-1","Parent6NodeName":null,"Parent6NodePriority":0,"EventNodeTypeId":12,"TypeFilterList":null}},{"Key":"2822347534","Value":{"Odd":250.0,"SortOrder":0,"Tax":"Tax1|0,00|S;Tax2|0,00|S","GameTypeResultsNr":-1,"ParentUniqueId":null,"Parent2UniqueId":null,"Parent3UniqueId":"8610ff0f-8750-429c-8c3d-0938ff2f2f43","IsLive":false,"LastUpdated":"2020-06-25T08:00:20.8089325+02:00","NodeName":"Sacramento Kings","NodeId":"2822347534","Type":12,"IsActive":true,"SportHandle":"basketball","Priority":0,"CountryCode":"","ParentNodeId":"2822347508","ParentNodeName":"Ganador","ParentNodePriority":9980,"DisplayTypeName":"","Parent2NodeId":"2822346263","Parent2NodeName":"NBA 2019/2020 - Campeonato NBA (Play-Off Incluido)","Parent2NodePriority":9980,"Parent3NodeId":"461719819","Parent3NodeName":"Apuestas Anticipadas - NBA","Parent3NodePriority":9980,"Parent4NodeId":"358491826","Parent4NodeName":"EE.UU.","Parent4NodePriority":9900,"Parent5NodeId":"358491795","Parent5NodeName":"Baloncesto","Parent5NodePriority":10,"Parent6NodeId":"-1","Parent6NodeName":null,"Parent6NodePriority":0,"EventNodeTypeId":12,"TypeFilterList":null}},{"Key":"2822347535","Value":{"Odd":300.0,"SortOrder":0,"Tax":"Tax1|0,00|S;Tax2|0,00|S","GameTypeResultsNr":-1,"ParentUniqueId":null,"Parent2UniqueId":null,"Parent3UniqueId":"8610ff0f-8750-429c-8c3d-0938ff2f2f43","IsLive":false,"LastUpdated":"2020-06-25T08:00:20.8089325+02:00","NodeName":"Washington Wizards","NodeId":"2822347535","Type":12,"IsActive":true,"SportHandle":"basketball","Priority":0,"CountryCode":"","ParentNodeId":"2822347508","ParentNodeName":"Ganador","ParentNodePriority":9980,"DisplayTypeName":"","Parent2NodeId":"2822346263","Parent2NodeName":"NBA 2019/2020 - Campeonato NBA (Play-Off Incluido)","Parent2NodePriority":9980,"Parent3NodeId":"461719819","Parent3NodeName":"Apuestas Anticipadas - NBA","Parent3NodePriority":9980,"Parent4NodeId":"358491826","Parent4NodeName":"EE.UU.","Parent4NodePriority":9900,"Parent5NodeId":"358491795","Parent5NodeName":"Baloncesto","Parent5NodePriority":10,"Parent6NodeId":"-1","Parent6NodeName":null,"Parent6NodePriority":0,"EventNodeTypeId":12,"TypeFilterList":null}},{"Key":"2822347536","Value":{"Odd":500.0,"SortOrder":0,"Tax":"Tax1|0,00|S;Tax2|0,00|S","GameTypeResultsNr":-1,"ParentUniqueId":null,"Parent2UniqueId":null,"Parent3UniqueId":"8610ff0f-8750-429c-8c3d-0938ff2f2f43","IsLive":false,"LastUpdated":"2020-06-25T08:00:20.8089325+02:00","NodeName":"Phoenix Suns","NodeId":"2822347536","Type":12,"IsActive":true,"SportHandle":"basketball","Priority":0,"CountryCode":"","ParentNodeId":"2822347508","ParentNodeName":"Ganador","ParentNodePriority":9980,"DisplayTypeName":"","Parent2NodeId":"2822346263","Parent2NodeName":"NBA 2019/2020 - Campeonato NBA (Play-Off Incluido)","Parent2NodePriority":9980,"Parent3NodeId":"461719819","Parent3NodeName":"Apuestas Anticipadas - NBA","Parent3NodePriority":9980,"Parent4NodeId":"358491826","Parent4NodeName":"EE.UU.","Parent4NodePriority":9900,"Parent5NodeId":"358491795","Parent5NodeName":"Baloncesto","Parent5NodePriority":10,"Parent6NodeId":"-1","Parent6NodeName":null,"Parent6NodePriority":0,"EventNodeTypeId":12,"TypeFilterList":null}}]