<?xml version="1.0" encoding="utf-8"?><Sport Name="Snooker" PageTitle="Filtered applied. MarketID: 140157 " TimeStamp="22/06/20 11:18:49"><EventGroup name="Tour Championship 2020" ID="20692572"><Event Name="Judd Trump vs Stephen Maguire" ID="-2137975531"><Market Name="1st Frame - Race to 30" ID="140157" FID="90402827" StartTime="24/06/20 13:30:00" EventComment="" PlaceTerms="1, 1/1"><Participant Name="Judd Trump" Odds="4/7" OddsDecimal="1.57" OddsAmerican="-175" Handicap="" ID="834060937" LastUpdated="21/06/20 20:48:24" AVG="8AF0684773A64EDDF97F54EAF83464473386BA6F" /><Participant Name="Stephen Maguire" Odds="5/4" OddsDecimal="2.25" OddsAmerican="125" Handicap="" ID="834060938" LastUpdated="21/06/20 20:48:24" AVG="45077B966A390351AD12958C62BD0AA3876798C2" /></Market></Event><Event Name="Shaun Murphy vs Mark Allen" ID="-1814758193"><Market Name="1st Frame - Race to 30" ID="140157" FID="89870369" StartTime="23/06/20 13:30:00" EventComment="" PlaceTerms="1, 1/1"><Participant Name="Shaun Murphy" Odds="4/5" OddsDecimal="1.80" OddsAmerican="-125" Handicap="" ID="801340158" LastUpdated="05/06/20 18:35:35" AVG="D55151390BBDB2CAC6E170B788DFD3194430C363" /><Participant Name="Mark Allen" Odds="10/11" OddsDecimal="1.90" OddsAmerican="-110" Handicap="" ID="801340160" LastUpdated="05/06/20 18:35:35" AVG="3C99E551183A2DCE492A23204709B0C8C5140546" /></Market></Event><Event Name="Mark Selby vs Yan Bingtao" ID="514646472"><Market Name="1st Frame - Race to 30" ID="140157" FID="89870362" StartTime="22/06/20 13:30:00" EventComment="" PlaceTerms="1, 1/1"><Participant Name="Mark Selby" Odds="8/11" OddsDecimal="1.72" OddsAmerican="-138" Handicap="" ID="801340159" LastUpdated="05/06/20 18:35:16" AVG="728899A8150BF5B76977C56754524FE794E83D11" /><Participant Name="Yan Bingtao" Odds="1/1" OddsDecimal="2.00" OddsAmerican="100" Handicap="" ID="801340161" LastUpdated="05/06/20 18:35:16" AVG="DF3CFE1441A26ECA5147E68A1CEABCEB1D4BAB64" /></Market></Event></EventGroup></Sport>