{"events":[{"event":{"id":1006463095,"name":"England - West Indies","nameDelimiter":"-","englishName":"England - West Indies","homeName":"England","awayName":"West Indies","start":"2020-07-08T10:00:00Z","group":"Matches","groupId":2000125178,"path":[{"id":1000093178,"name":"Cricket","englishName":"Cricket","termKey":"cricket"},{"id":2000085729,"name":"International Test Cricket","englishName":"International Test Cricket","termKey":"international_test_cricket"},{"id":2000125178,"name":"Matches","englishName":"Matches","termKey":"matches"}],"nonLiveBoCount":6,"sport":"CRICKET","tags":["OFFERED_LIVE","MATCH"],"state":"NOT_STARTED","participants":[{"participantId":1000000544,"name":"England","scratched":false,"nonRunner":false,"home":true,"participantType":"TEAM"},{"participantId":1000016045,"name":"West Indies","scratched":false,"nonRunner":false,"home":false,"participantType":"TEAM"}],"extraInfo":"1st Test"},"betOffers":[{"id":2215368021,"closed":"2020-07-08T10:00:00Z","criterion":{"id":1001214599,"label":"Moneyline","englishLabel":"Match Odds","order":[]},"betOfferType":{"id":2,"name":"Match","englishName":"Match"},"eventId":1006463095,"outcomes":[{"id":2755017902,"label":"1","englishLabel":"1","odds":1250,"participant":"England","type":"OT_ONE","betOfferId":2215368021,"changedDate":"2020-06-15T11:34:56Z","participantId":1000000544,"oddsFractional":"1/4","oddsAmerican":"-400","status":"OPEN","cashOutStatus":"ENABLED"},{"id":2755017903,"label":"X","englishLabel":"X","odds":6250,"type":"OT_CROSS","betOfferId":2215368021,"changedDate":"2020-06-15T11:34:56Z","oddsFractional":"21/4","oddsAmerican":"525","status":"OPEN","cashOutStatus":"ENABLED"},{"id":2755017904,"label":"2","englishLabel":"2","odds":9500,"participant":"West Indies","type":"OT_TWO","betOfferId":2215368021,"changedDate":"2020-06-15T11:34:56Z","participantId":1000016045,"oddsFractional":"17/2","oddsAmerican":"850","status":"OPEN","cashOutStatus":"ENABLED"}],"tags":["OFFERED_PREMATCH","MAIN"],"sortOrder":1,"cashOutStatus":"ENABLED"}]},{"event":{"id":1006463117,"name":"England - West Indies","nameDelimiter":"-","englishName":"England - West Indies","homeName":"England","awayName":"West Indies","start":"2020-07-24T10:01:00Z","group":"Series","groupId":2000125179,"path":[{"id":1000093178,"name":"Cricket","englishName":"Cricket","termKey":"cricket"},{"id":2000085729,"name":"International Test Cricket","englishName":"International Test Cricket","termKey":"international_test_cricket"},{"id":2000125179,"name":"Series","englishName":"Series","termKey":"series"}],"nonLiveBoCount":4,"sport":"CRICKET","tags":["MATCH"],"state":"NOT_STARTED","participants":[{"participantId":1000000544,"name":"England","scratched":false,"nonRunner":false,"home":true,"participantType":"TEAM"},{"participantId":1000016045,"name":"West Indies","scratched":false,"nonRunner":false,"home":false,"participantType":"TEAM"}]},"betOffers":[]},{"event":{"id":1006216606,"name":"Australia - England","nameDelimiter":"-","englishName":"Australia - England","homeName":"Australia","awayName":"England","start":"2021-11-22T21:00:00Z","group":"Series","groupId":2000054280,"path":[{"id":1000093178,"name":"Cricket","englishName":"Cricket","termKey":"cricket"},{"id":1000093838,"name":"The Ashes","englishName":"The Ashes","termKey":"the_ashes"},{"id":2000054280,"name":"Series","englishName":"Series","termKey":"series"}],"nonLiveBoCount":1,"sport":"CRICKET","tags":["MATCH"],"state":"NOT_STARTED","participants":[{"participantId":1000000545,"name":"Australia","scratched":false,"nonRunner":false,"home":true,"participantType":"TEAM"},{"participantId":1000000544,"name":"England","scratched":false,"nonRunner":false,"home":false,"participantType":"TEAM"}]},"betOffers":[]}],"terms":[{"type":"SPORT","id":"/cricket","termKey":"cricket","localizedName":"Cricket","parentId":"/","englishName":"Cricket"}],"activeTermIds":["/cricket"],"soonMode":"MONTHLY","categoryGroups":[{"categoryGroupName":"list_view","categories":[{"id":12919,"englishName":"Series","localizedName":"Series"}]},{"categoryGroupName":"combined_layout","categories":[{"id":14459,"englishName":"Match","localizedName":"Moneyline"}],"localizedName":"Moneyline"}],"activeCategories":["14459"],"activeEventTypes":["matches"],"eventTypes":["competitions","matches"],"defaultEventType":"matches"}